{"count":861970,"next":"https://api.rawg.io/api/games?key=e5af9c0ecbb74eb68b32eb1dc1142b2b&ordering=-metacritic&page=2","previous":null,"results":[{"id":25097,"slug":"the-legend-of-zelda-ocarina-of-time","name":"The Legend of Zelda: Ocarina of Time","released":"1998-11-21","tba":false,"background_image":"https://media.rawg.io/media/games/3a0/3a0c8e9ed3a711c542218831b893a0fa.jpg","rating":4.39,"rating_top":5,"ratings":[{"id":5,"title":"exceptional","count":527,"percent":64.66},{"id":4,"title":"recommended","count":183,"percent":22.45},{"id":3,"title":"meh","count":54,"percent":6.63},{"id":1,"title":"skip","count":51,"percent":6.26}],"ratings_count":808,"reviews_text_count":5,"added":1682,"added_by_status":{"yet":108,"owned":426,"beaten":733,"toplay":197,"dropped":170,"playing":48},"metacritic":99,"playtime":7,"suggestions_count":343,"updated":"2024-01-20T16:04:34","user_game":null,"reviews_count":815,"saturated_color":"0f0f0f","dominant_color":"0f0f0f","platforms":[{"platform":{"id":7,"name":"Nintendo Switch","slug":"nintendo-switch","image":null,"year_end":null,"year_start":null,"games_count":5380,"image_background":"https://media.rawg.io/media/games/f99/f9979698c43fd84c3ab69280576dd3af.jpg"},"released_at":"1998-11-21","requirements_en":null,"requirements_ru":null},{"platform":{"id":83,"name":"Nintendo 64","slug":"nintendo-64","image":null,"year_end":null,"year_start":null,"games_count":363,"image_background":"https://media.rawg.io/media/screenshots/4cf/4cf1e2b4cd701605225fb443d5e84f77.jpg"},"released_at":"1998-11-21","requirements_en":null,"requirements_ru":null}],"parent_platforms":[{"platform":{"id":7,"name":"Nintendo","slug":"nintendo"}}],"genres":[{"id":4,"name":"Action","slug":"action","games_count":177743,"image_background":"https://media.rawg.io/media/games/49c/49c3dfa4ce2f6f140cc4825868e858cb.jpg"},{"id":3,"name":"Adventure","slug":"adventure","games_count":137364,"image_background":"https://media.rawg.io/media/games/562/562553814dd54e001a541e4ee83a591c.jpg"},{"id":5,"name":"RPG","slug":"role-playing-games-rpg","games_count":54782,"image_background":"https://media.rawg.io/media/games/1f4/1f47a270b8f241e4676b14d39ec620f7.jpg"}],"stores":[{"id":29484,"store":{"id":6,"name":"Nintendo Store","slug":"nintendo","domain":"nintendo.com","games_count":8946,"image_background":"https://media.rawg.io/media/games/f99/f9979698c43fd84c3ab69280576dd3af.jpg"}}],"clip":null,"tags":[{"id":31,"name":"Singleplayer","slug":"singleplayer","language":"eng","games_count":216849,"image_background":"https://media.rawg.io/media/games/4a0/4a0a1316102366260e6f38fd2a9cfdce.jpg"}],"esrb_rating":{"id":1,"name":"Everyone","slug":"everyone"},"short_screenshots":[{"id":-1,"image":"https://media.rawg.io/media/games/3a0/3a0c8e9ed3a711c542218831b893a0fa.jpg"},{"id":248572,"image":"https://media.rawg.io/media/screenshots/aff/aff922f4dfbc562ab31b5b924adbfe93.jpg"},{"id":248573,"image":"https://media.rawg.io/media/screenshots/40a/40aa860328a2295da73336d4060bd973.jpg"},{"id":248574,"image":"https://media.rawg.io/media/screenshots/e72/e72b59594b6abdedf8adbfd5a0e53251.jpg"},{"id":248575,"image":"https://media.rawg.io/media/screenshots/070/070de3718e543e7ac533d09a8758775f.jpg"},{"id":248576,"image":"https://media.rawg.io/media/screenshots/f75/f75e8f877f1851461aba7579ef604f77.jpg"},{"id":248577,"image":"https://media.rawg.io/media/screenshots/f26/f26c6649ce30ae53204aa7f76350b2fd.jpg"}]},{"id":407559,"slug":"soulcalibur-1998","name":"Soulcalibur (1998)","released":"1998-07-30","tba":false,"background_image":null,"rating":0,"rating_top":0,"ratings":[],"ratings_count":0,"reviews_text_count":0,"added":1,"added_by_status":{"yet":1},"metacritic":98,"playtime":0,"suggestions_count":0,"updated":"2020-01-29T13:45:49","user_game":null,"reviews_count":0,"community_rating":0,"saturated_color":"0f0f0f","dominant_color":"0f0f0f","platforms":[{"platform":{"id":106,"name":"Dreamcast","slug":"dreamcast","image":null,"year_end":null,"year_start":null,"games_count":360,"image_background":"https://media.rawg.io/media/games/4cb/4cb463b5588adc672124fb041f09e91c.jpg"},"released_at":"1998-07-30","requirements_en":null,"requirements_ru":null},{"platform":{"id":14,"name":"Xbox 360","slug":"xbox360","image":null,"year_end":null,"year_start":null,"games_count":2787,"image_background":"https://media.rawg.io/media/games/15c/15c95a4915f88a3e89c821526afe05fc.jpg"},"released_at":"1998-07-30","requirements_en":null,"requirements_ru":null}],"parent_platforms":[{"platform":{"id":3,"name":"Xbox","slug":"xbox"}},{"platform":{"id":11,"name":"SEGA","slug":"sega"}}],"genres":[{"id":6,"name":"Fighting","slug":"fighting","games_count":11746,"image_background":"https://media.rawg.io/media/games/234/23410661770ae13eac11066980834367.jpg"}],"stores":[],"clip":null,"tags":[],"esrb_rating":{"id":3,"name":"Teen","slug":"teen"},"short_screenshots":[]},{"id":54751,"slug":"soulcalibur","name":"Soulcalibur","released":"1998-07-30","tba":false,"background_image":"https://media.rawg.io/media/games/743/7430f1846ba6ce836f169d936c89819e.jpg","rating":4.39,"rating_top":5,"ratings":[{"id":5,"title":"exceptional","count":44,"percent":53.01},{"id":4,"title":"recommended","count":31,"percent":37.35},{"id":3,"title":"meh","count":6,"percent":7.23},{"id":1,"title":"skip","count":2,"percent":2.41}],"ratings_count":82,"reviews_text_count":1,"added":283,"added_by_status":{"yet":13,"owned":161,"beaten":66,"toplay":16,"dropped":26,"playing":1},"metacritic":98,"playtime":6,"suggestions_count":403,"updated":"2023-11-22T04:51:52","user_game":null,"reviews_count":83,"saturated_color":"0f0f0f","dominant_color":"0f0f0f","platforms":[{"platform":{"id":1,"name":"Xbox One","slug":"xbox-one","image":null,"year_end":null,"year_start":null,"games_count":5570,"image_background":"https://media.rawg.io/media/games/8d6/8d69eb6c32ed6acfd75f82d532144993.jpg"},"released_at":"1998-07-30","requirements_en":null,"requirements_ru":null},{"platform":{"id":3,"name":"iOS","slug":"ios","image":null,"year_end":null,"year_start":null,"games_count":77183,"image_background":"https://media.rawg.io/media/games/e74/e74458058b35e01c1ae3feeb39a3f724.jpg"},"released_at":"1998-07-30","requirements_en":null,"requirements_ru":null},{"platform":{"id":14,"name":"Xbox 360","slug":"xbox360","image":null,"year_end":null,"year_start":null,"games_count":2787,"image_background":"https://media.rawg.io/media/games/15c/15c95a4915f88a3e89c821526afe05fc.jpg"},"released_at":"1998-07-30","requirements_en":null,"requirements_ru":null},{"platform":{"id":21,"name":"Android","slug":"android","image":null,"year_end":null,"year_start":null,"games_count":52312,"image_background":"https://media.rawg.io/media/games/be0/be084b850302abe81675bc4ffc08a0d0.jpg"},"released_at":"1998-07-30","requirements_en":null,"requirements_ru":null},{"platform":{"id":106,"name":"Dreamcast","slug":"dreamcast","image":null,"year_end":null,"year_start":null,"games_count":360,"image_background":"https://media.rawg.io/media/games/4cb/4cb463b5588adc672124fb041f09e91c.jpg"},"released_at":"1998-07-30","requirements_en":null,"requirements_ru":null}],"parent_platforms":[{"platform":{"id":3,"name":"Xbox","slug":"xbox"}},{"platform":{"id":4,"name":"iOS","slug":"ios"}},{"platform":{"id":8,"name":"Android","slug":"android"}},{"platform":{"id":11,"name":"SEGA","slug":"sega"}}],"genres":[{"id":4,"name":"Action","slug":"action","games_count":177743,"image_background":"https://media.rawg.io/media/games/49c/49c3dfa4ce2f6f140cc4825868e858cb.jpg"},{"id":6,"name":"Fighting","slug":"fighting","games_count":11746,"image_background":"https://media.rawg.io/media/games/234/23410661770ae13eac11066980834367.jpg"}],"stores":[{"id":233441,"store":{"id":7,"name":"Xbox 360 Store","slug":"xbox360","domain":"marketplace.xbox.com","games_count":1912,"image_background":"https://media.rawg.io/media/games/960/960b601d9541cec776c5fa42a00bf6c4.jpg"}}],"clip":null,"tags":[{"id":418,"name":"2 players","slug":"2-players","language":"eng","games_count":1244,"image_background":"https://media.rawg.io/media/games/5b4/5b4af50ce68cf94dcab24f3dba33eaab.jpg"}],"esrb_rating":null,"short_screenshots":[{"id":-1,"image":"https://media.rawg.io/media/games/743/7430f1846ba6ce836f169d936c89819e.jpg"},{"id":742333,"image":"https://media.rawg.io/media/screenshots/9a6/9a629f689c5046e8a540bee2fc5d9886.jpg"},{"id":2006773,"image":"https://media.rawg.io/media/screenshots/ef0/ef065a3a1a2669096285e697d48123ac.jpg"},{"id":2006774,"image":"https://media.rawg.io/media/screenshots/d3c/d3c0a4a32e6580082fe2a817b68d3738.jpg"},{"id":2006775,"image":"https://media.rawg.io/media/screenshots/452/4525e59360ba76ed0b64c06fa35c54b2.jpg"},{"id":2006776,"image":"https://media.rawg.io/media/screenshots/b44/b44045d72c82f0392e86de9ce4d10540.jpg"},{"id":2006777,"image":"https://media.rawg.io/media/screenshots/9b1/9b173e96f83d2d77770f9b00f2562fa9.jpg"}]},{"id":324997,"slug":"baldurs-gate-3","name":"Baldur's Gate III","released":"2023-08-03","tba":false,"background_image":"https://media.rawg.io/media/games/699/69907ecf13f172e9e144069769c3be73.jpg","rating":4.57,"rating_top":5,"ratings":[{"id":5,"title":"exceptional","count":350,"percent":75.27},{"id":4,"title":"recommended","count":72,"percent":15.48},{"id":3,"title":"meh","count":22,"percent":4.73},{"id":1,"title":"skip","count":21,"percent":4.52}],"ratings_count":448,"reviews_text_count":12,"added":2843,"added_by_status":{"yet":279,"owned":1222,"beaten":232,"toplay":749,"dropped":94,"playing":267},"metacritic":97,"playtime":9,"suggestions_count":570,"updated":"2024-01-22T23:20:28","user_game":null,"reviews_count":465,"saturated_color":"0f0f0f","dominant_color":"0f0f0f","platforms":[{"platform":{"id":5,"name":"macOS","slug":"macos","image":null,"year_end":null,"year_start":null,"games_count":103224,"image_background":"https://media.rawg.io/media/games/2ba/2bac0e87cf45e5b508f227d281c9252a.jpg"},"released_at":"2023-08-03","requirements_en":{"minimum":"Minimum:\r\n\r\nRequires a 64-bit processor and operating system\r\n\r\nOS: macOS 10.15.6\r\n\r\nProcessor: 2.6GHz Quad-Core Intel Core i7\r\n\r\nMemory: 8 GB RAM\r\n\r\nGraphics: AMD Radeon460 4GB\r\n\r\nStorage: 150 GB available space\r\n\r\nAdditional Notes: Minimum specs can run the game on low to medium settings. To meet minimum specs, you'll need a MacBook Pro 15 inch from 2016 or newer. Or, a MacBook Pro 13 inch from 2018 or newer. M1 Chip requirements: MacBook Air, MacBook Pro, or Mac mini with Apple M1 chip and 8GB of RAM.","recommended":"Recommended:\r\n\r\nRequires a 64-bit processor and operating system\r\n\r\nOS: macOS 10.15.7\r\n\r\nProcessor: 2.3GHz 8-Core Intel Core i9\r\n\r\nMemory: 16 GB RAM\r\n\r\nGraphics: AMD Radeon Pro 5500M 8GB\r\n\r\nStorage: 150 GB available space\r\n\r\nAdditional Notes: Recommended specs can run the game on high or ultra settings. You'll meet recommended specs if you have a MacBook Pro 15 inch or 16 inch from 2019 and up. An iMac from 2017 or newer will also pull it off. M1 Chip requirements: MacBook Air, MacBook Pro, or Mac mini with Apple M1 chip and 16GB of RAM"},"requirements_ru":null},{"platform":{"id":4,"name":"PC","slug":"pc","image":null,"year_end":null,"year_start":null,"games_count":524416,"image_background":"https://media.rawg.io/media/games/120/1201a40e4364557b124392ee50317b99.jpg"},"released_at":"2023-08-03","requirements_en":{"minimum":"Minimum:\r\n\r\nRequires a 64-bit processor and operating system\r\n\r\nOS: Windows 7 SP1 64-bit\r\n\r\nProcessor: Intel i5-4690 / AMD FX 4350\r\n\r\nMemory: 8 GB RAM\r\n\r\nGraphics: Nvidia GTX 780 / AMD Radeon R9 280X\r\n\r\nDirectX: Version 11\r\n\r\nStorage: 150 GB available space\r\n\r\nAdditional Notes: Default API is Vulkan 1.1. Directx11 API also provided. The minimum requirements might decrease over the course of Early Access, as performance improves.","recommended":"Recommended:\r\n\r\nRequires a 64-bit processor and operating system\r\n\r\nOS: Windows 10 64-bit\r\n\r\nProcessor: Intel i7 4770k / AMD Ryzen 5 1500X\r\n\r\nMemory: 16 GB RAM\r\n\r\nGraphics: Nvidia GTX 1060 6GB / AMD RX580\r\n\r\nDirectX: Version 11\r\n\r\nStorage: 150 GB available space\r\n\r\nAdditional Notes: Default API is Vulkan 1.1. Directx11 API also provided. The recommended requirements might decrease over the course of Early Access, as performance improves."},"requirements_ru":null},{"platform":{"id":187,"name":"PlayStation 5","slug":"playstation5","image":null,"year_end":null,"year_start":2020,"games_count":994,"image_background":"https://media.rawg.io/media/games/b34/b3419c2706f8f8dbe40d08e23642ad06.jpg"},"released_at":"2023-08-03","requirements_en":null,"requirements_ru":null}],"parent_platforms":[{"platform":{"id":1,"name":"PC","slug":"pc"}},{"platform":{"id":2,"name":"PlayStation","slug":"playstation"}},{"platform":{"id":5,"name":"Apple Macintosh","slug":"mac"}}],"genres":[{"id":3,"name":"Adventure","slug":"adventure","games_count":137363,"image_background":"https://media.rawg.io/media/games/995/9951d9d55323d08967640f7b9ab3e342.jpg"},{"id":5,"name":"RPG","slug":"role-playing-games-rpg","games_count":54782,"image_background":"https://media.rawg.io/media/games/1f4/1f47a270b8f241e4676b14d39ec620f7.jpg"},{"id":10,"name":"Strategy","slug":"strategy","games_count":55119,"image_background":"https://media.rawg.io/media/games/238/2383a172b4d50a7b44e07980eb7141ea.jpg"}],"stores":[{"id":930049,"store":{"id":3,"name":"PlayStation Store","slug":"playstation-store","domain":"store.playstation.com","games_count":7878,"image_background":"https://media.rawg.io/media/games/157/15742f2f67eacff546738e1ab5c19d20.jpg"}},{"id":326833,"store":{"id":5,"name":"GOG","slug":"gog","domain":"gog.com","games_count":5744,"image_background":"https://media.rawg.io/media/games/8e4/8e4de3f54ac659e08a7ba6a2b731682a.jpg"}},{"id":326832,"store":{"id":1,"name":"Steam","slug":"steam","domain":"store.steampowered.com","games_count":87632,"image_background":"https://media.rawg.io/media/games/490/49016e06ae2103881ff6373248843069.jpg"}}],"clip":null,"tags":[{"id":31,"name":"Singleplayer","slug":"singleplayer","language":"eng","games_count":216849,"image_background":"https://media.rawg.io/media/games/4a0/4a0a1316102366260e6f38fd2a9cfdce.jpg"},{"id":40847,"name":"Steam Achievements","slug":"steam-achievements","language":"eng","games_count":35163,"image_background":"https://media.rawg.io/media/games/310/3106b0e012271c5ffb16497b070be739.jpg"},{"id":7,"name":"Multiplayer","slug":"multiplayer","language":"eng","games_count":36937,"image_background":"https://media.rawg.io/media/games/587/587588c64afbff80e6f444eb2e46f9da.jpg"},{"id":40849,"name":"Steam Cloud","slug":"steam-cloud","language":"eng","games_count":16509,"image_background":"https://media.rawg.io/media/games/490/49016e06ae2103881ff6373248843069.jpg"},{"id":24,"name":"RPG","slug":"rpg","language":"eng","games_count":19541,"image_background":"https://media.rawg.io/media/games/b45/b45575f34285f2c4479c9a5f719d972e.jpg"},{"id":18,"name":"Co-op","slug":"co-op","language":"eng","games_count":10953,"image_background":"https://media.rawg.io/media/games/737/737ea5662211d2e0bbd6f5989189e4f1.jpg"},{"id":9,"name":"Online Co-Op","slug":"online-co-op","language":"eng","games_count":5123,"image_background":"https://media.rawg.io/media/games/21c/21cc15d233117c6809ec86870559e105.jpg"},{"id":64,"name":"Fantasy","slug":"fantasy","language":"eng","games_count":26503,"image_background":"https://media.rawg.io/media/games/1f4/1f47a270b8f241e4676b14d39ec620f7.jpg"},{"id":198,"name":"Split Screen","slug":"split-screen","language":"eng","games_count":6314,"image_background":"https://media.rawg.io/media/games/33b/33b825c76382931df0fd8ecddf5caebe.jpg"},{"id":397,"name":"Online multiplayer","slug":"online-multiplayer","language":"eng","games_count":3804,"image_background":"https://media.rawg.io/media/games/21b/21babfc41e2a6972290833d1b860f13e.jpg"},{"id":75,"name":"Local Co-Op","slug":"local-co-op","language":"eng","games_count":5262,"image_background":"https://media.rawg.io/media/games/d1a/d1a1202a378607b6c635c8f18ace95dd.jpg"},{"id":72,"name":"Local Multiplayer","slug":"local-multiplayer","language":"eng","games_count":12914,"image_background":"https://media.rawg.io/media/games/9f1/9f1891779cb20f44de93cef33b067e50.jpg"},{"id":40832,"name":"Cross-Platform Multiplayer","slug":"cross-platform-multiplayer","language":"eng","games_count":2483,"image_background":"https://media.rawg.io/media/games/48e/48e63bbddeddbe9ba81942772b156664.jpg"},{"id":468,"name":"role-playing","slug":"role-playing","language":"eng","games_count":1547,"image_background":"https://media.rawg.io/media/games/598/59851e152a6898c8bf79069b5bf2f4db.jpg"},{"id":121,"name":"Character Customization","slug":"character-customization","language":"eng","games_count":4200,"image_background":"https://media.rawg.io/media/games/dc0/dc0926d3f84ffbcc00968fe8a6f0aed3.jpg"},{"id":40833,"name":"Captions available","slug":"captions-available","language":"eng","games_count":1302,"image_background":"https://media.rawg.io/media/games/490/49016e06ae2103881ff6373248843069.jpg"},{"id":99,"name":"Isometric","slug":"isometric","language":"eng","games_count":4255,"image_background":"https://media.rawg.io/media/games/840/8408ad3811289a6a5830cae60fb0b62a.jpg"},{"id":82,"name":"Magic","slug":"magic","language":"eng","games_count":8912,"image_background":"https://media.rawg.io/media/games/516/516c6bfe36ddb498d860f68927448a75.jpg"},{"id":40937,"name":"Steam Trading Cards","slug":"steam-trading-cards-2","language":"eng","games_count":588,"image_background":"https://media.rawg.io/media/games/a4b/a4bb55f42fe837ae7bf1307e7b41cc85.jpg"},{"id":238,"name":"CRPG","slug":"crpg","language":"eng","games_count":928,"image_background":"https://media.rawg.io/media/games/789/7896837ec22a83e4007018ddd55e8c9a.jpg"},{"id":206,"name":"Party-Based RPG","slug":"party-based-rpg","language":"eng","games_count":940,"image_background":"https://media.rawg.io/media/games/add/add07a75a3f1e479b55dbe920d9fb13d.jpg"},{"id":467,"name":"Role Playing Game","slug":"role-playing-game","language":"eng","games_count":19,"image_background":"https://media.rawg.io/media/games/8ea/8ea1e2850d7568bc9733d546c0ac6ce1.jpg"},{"id":574,"name":"Dungeons & Dragons","slug":"dungeons-dragons","language":"eng","games_count":181,"image_background":"https://media.rawg.io/media/games/246/246367eab7ccfaaad14ad4507deee067.jpeg"}],"esrb_rating":{"id":4,"name":"Mature","slug":"mature"},"short_screenshots":[{"id":-1,"image":"https://media.rawg.io/media/games/699/69907ecf13f172e9e144069769c3be73.jpg"},{"id":2300708,"image":"https://media.rawg.io/media/screenshots/a67/a676cdec0eadc42a133ac49e7f2e1aac.jpg"},{"id":2300709,"image":"https://media.rawg.io/media/screenshots/705/705846f6583a6da009a0ae7fcdece36d.jpg"},{"id":2300710,"image":"https://media.rawg.io/media/screenshots/d29/d29b1d2726d69432d2b4180a79b9ee9d.jpg"},{"id":2300711,"image":"https://media.rawg.io/media/screenshots/ed1/ed19ec8ce43f9dd3553df4a6d9301f61.jpg"},{"id":2300712,"image":"https://media.rawg.io/media/screenshots/6c8/6c8983d658a4a24dc8eb9d2f88f1dabf.jpg"},{"id":2300713,"image":"https://media.rawg.io/media/screenshots/92c/92cbe16a795afbc9d9837ed9eae4f22b.jpg"}]},{"id":56123,"slug":"metroid-prime","name":"Metroid Prime","released":"2002-11-17","tba":false,"background_image":"https://media.rawg.io/media/games/c86/c86bc047ba949959a90fe24209d59439.jpg","rating":4.38,"rating_top":5,"ratings":[{"id":5,"title":"exceptional","count":154,"percent":62.6},{"id":4,"title":"recommended","count":57,"percent":23.17},{"id":3,"title":"meh","count":22,"percent":8.94},{"id":1,"title":"skip","count":13,"percent":5.28}],"ratings_count":241,"reviews_text_count":5,"added":589,"added_by_status":{"yet":60,"owned":133,"beaten":194,"toplay":110,"dropped":75,"playing":17},"metacritic":97,"playtime":2,"suggestions_count":348,"updated":"2024-01-13T08:44:04","user_game":null,"reviews_count":246,"saturated_color":"0f0f0f","dominant_color":"0f0f0f","platforms":[{"platform":{"id":11,"name":"Wii","slug":"wii","image":null,"year_end":null,"year_start":null,"games_count":2232,"image_background":"https://media.rawg.io/media/games/341/3413d7275fb1e919f00a925df8288b77.jpg"},"released_at":"2002-11-17","requirements_en":null,"requirements_ru":null},{"platform":{"id":105,"name":"GameCube","slug":"gamecube","image":null,"year_end":null,"year_start":null,"games_count":633,"image_background":"https://media.rawg.io/media/games/33d/33d72d63a624f17431d39922359c7bf8.jpg"},"released_at":"2002-11-17","requirements_en":null,"requirements_ru":null}],"parent_platforms":[{"platform":{"id":7,"name":"Nintendo","slug":"nintendo"}}],"genres":[{"id":4,"name":"Action","slug":"action","games_count":177743,"image_background":"https://media.rawg.io/media/games/49c/49c3dfa4ce2f6f140cc4825868e858cb.jpg"},{"id":2,"name":"Shooter","slug":"shooter","games_count":59432,"image_background":"https://media.rawg.io/media/games/34b/34b1f1850a1c06fd971bc6ab3ac0ce0e.jpg"},{"id":3,"name":"Adventure","slug":"adventure","games_count":137364,"image_background":"https://media.rawg.io/media/games/562/562553814dd54e001a541e4ee83a591c.jpg"}],"stores":[],"clip":null,"tags":[{"id":31,"name":"Singleplayer","slug":"singleplayer","language":"eng","games_count":216849,"image_background":"https://media.rawg.io/media/games/4a0/4a0a1316102366260e6f38fd2a9cfdce.jpg"}],"esrb_rating":null,"short_screenshots":[{"id":-1,"image":"https://media.rawg.io/media/games/c86/c86bc047ba949959a90fe24209d59439.jpg"},{"id":752887,"image":"https://media.rawg.io/media/screenshots/ab7/ab7efedd1d85fb0007f84a2955ac9d39.jpg"},{"id":752888,"image":"https://media.rawg.io/media/screenshots/788/78816464d5fddfa7f81b892b9b7c6a39.jpg"},{"id":752889,"image":"https://media.rawg.io/media/screenshots/6d9/6d9a1de06e87730707e4f39acd6cc237.jpg"},{"id":752890,"image":"https://media.rawg.io/media/screenshots/c11/c11eaf445d1146cad23f499adbd86b85.jpg"},{"id":752891,"image":"https://media.rawg.io/media/screenshots/29f/29fb6ff5828089ce44aa0e82fe75b176.jpg"},{"id":752892,"image":"https://media.rawg.io/media/screenshots/4ca/4ca53cc663eeea9eb0652413ea4e8372.jpg"}]},{"id":28495,"slug":"perfect-dark","name":"Perfect Dark","released":"2000-05-22","tba":false,"background_image":"https://media.rawg.io/media/games/f62/f62d090119e5ff05c59036480123fd83.jpg","rating":3.97,"rating_top":5,"ratings":[{"id":5,"title":"exceptional","count":67,"percent":38.73},{"id":4,"title":"recommended","count":63,"percent":36.42},{"id":3,"title":"meh","count":28,"percent":16.18},{"id":1,"title":"skip","count":15,"percent":8.67}],"ratings_count":172,"reviews_text_count":1,"added":1026,"added_by_status":{"yet":59,"owned":765,"beaten":84,"toplay":47,"dropped":66,"playing":5},"metacritic":97,"playtime":10,"suggestions_count":411,"updated":"2023-09-25T15:46:45","user_game":null,"reviews_count":173,"saturated_color":"0f0f0f","dominant_color":"0f0f0f","platforms":[{"platform":{"id":14,"name":"Xbox 360","slug":"xbox360","image":null,"year_end":null,"year_start":null,"games_count":2787,"image_background":"https://media.rawg.io/media/games/15c/15c95a4915f88a3e89c821526afe05fc.jpg"},"released_at":"2000-05-22","requirements_en":null,"requirements_ru":null},{"platform":{"id":83,"name":"Nintendo 64","slug":"nintendo-64","image":null,"year_end":null,"year_start":null,"games_count":363,"image_background":"https://media.rawg.io/media/screenshots/4cf/4cf1e2b4cd701605225fb443d5e84f77.jpg"},"released_at":"2000-05-22","requirements_en":null,"requirements_ru":null}],"parent_platforms":[{"platform":{"id":3,"name":"Xbox","slug":"xbox"}},{"platform":{"id":7,"name":"Nintendo","slug":"nintendo"}}],"genres":[{"id":4,"name":"Action","slug":"action","games_count":177743,"image_background":"https://media.rawg.io/media/games/49c/49c3dfa4ce2f6f140cc4825868e858cb.jpg"},{"id":2,"name":"Shooter","slug":"shooter","games_count":59432,"image_background":"https://media.rawg.io/media/games/34b/34b1f1850a1c06fd971bc6ab3ac0ce0e.jpg"}],"stores":[{"id":465930,"store":{"id":2,"name":"Xbox Store","slug":"xbox-store","domain":"microsoft.com","games_count":4790,"image_background":"https://media.rawg.io/media/games/8d6/8d69eb6c32ed6acfd75f82d532144993.jpg"}},{"id":33681,"store":{"id":7,"name":"Xbox 360 Store","slug":"xbox360","domain":"marketplace.xbox.com","games_count":1912,"image_background":"https://media.rawg.io/media/games/960/960b601d9541cec776c5fa42a00bf6c4.jpg"}}],"clip":null,"tags":[{"id":37796,"name":"exclusive","slug":"exclusive","language":"eng","games_count":4500,"image_background":"https://media.rawg.io/media/games/f0e/f0e050dc774d4ae3afced76b33516295.jpg"}],"esrb_rating":{"id":4,"name":"Mature","slug":"mature"},"short_screenshots":[{"id":-1,"image":"https://media.rawg.io/media/games/f62/f62d090119e5ff05c59036480123fd83.jpg"},{"id":2467079,"image":"https://media.rawg.io/media/screenshots/fc8/fc8422a3a58544e239b3b215eea4ba25.jpg"},{"id":2467080,"image":"https://media.rawg.io/media/screenshots/1dd/1ddf2e386765e8737f840263eb821f84.jpg"},{"id":2467081,"image":"https://media.rawg.io/media/screenshots/560/56011aab7f5e7a58961f661dceb80511.jpg"},{"id":2467082,"image":"https://media.rawg.io/media/screenshots/9a4/9a4229fdb3a8fdaf0471ce9eb9084cda.jpg"},{"id":2467083,"image":"https://media.rawg.io/media/screenshots/f51/f510e9169256de968d96a57d981e398d.jpg"},{"id":2467084,"image":"https://media.rawg.io/media/screenshots/d34/d34fd0fc008e85f7a9a7f64da4ba2b6f.jpg"}]},{"id":28026,"slug":"super-mario-odyssey","name":"Super Mario Odyssey","released":"2017-10-27","tba":false,"background_image":"https://media.rawg.io/media/games/267/267bd0dbc496f52692487d07d014c061.jpg","rating":4.44,"rating_top":5,"ratings":[{"id":5,"title":"exceptional","count":1187,"percent":64.86},{"id":4,"title":"recommended","count":452,"percent":24.7},{"id":3,"title":"meh","count":99,"percent":5.41},{"id":1,"title":"skip","count":92,"percent":5.03}],"ratings_count":1799,"reviews_text_count":18,"added":3568,"added_by_status":{"yet":186,"owned":705,"beaten":1768,"toplay":446,"dropped":201,"playing":262},"metacritic":97,"playtime":0,"suggestions_count":458,"updated":"2024-01-22T15:27:54","user_game":null,"reviews_count":1830,"saturated_color":"0f0f0f","dominant_color":"0f0f0f","platforms":[{"platform":{"id":7,"name":"Nintendo Switch","slug":"nintendo-switch","image":null,"year_end":null,"year_start":null,"games_count":5380,"image_background":"https://media.rawg.io/media/games/f99/f9979698c43fd84c3ab69280576dd3af.jpg"},"released_at":"2017-10-27","requirements_en":null,"requirements_ru":null}],"parent_platforms":[{"platform":{"id":7,"name":"Nintendo","slug":"nintendo"}}],"genres":[{"id":11,"name":"Arcade","slug":"arcade","games_count":22632,"image_background":"https://media.rawg.io/media/games/297/297a51aa1f0999016d5a35e2e1d6d8ab.jpg"},{"id":83,"name":"Platformer","slug":"platformer","games_count":100745,"image_background":"https://media.rawg.io/media/games/04a/04a7e7e185fb51493bdcbe1693a8b3dc.jpg"}],"stores":[{"id":32920,"store":{"id":6,"name":"Nintendo Store","slug":"nintendo","domain":"nintendo.com","games_count":8946,"image_background":"https://media.rawg.io/media/games/f99/f9979698c43fd84c3ab69280576dd3af.jpg"}}],"clip":null,"tags":[{"id":31,"name":"Singleplayer","slug":"singleplayer","language":"eng","games_count":216849,"image_background":"https://media.rawg.io/media/games/4a0/4a0a1316102366260e6f38fd2a9cfdce.jpg"},{"id":72,"name":"Local Multiplayer","slug":"local-multiplayer","language":"eng","games_count":12914,"image_background":"https://media.rawg.io/media/games/9f1/9f1891779cb20f44de93cef33b067e50.jpg"},{"id":37796,"name":"exclusive","slug":"exclusive","language":"eng","games_count":4500,"image_background":"https://media.rawg.io/media/games/f0e/f0e050dc774d4ae3afced76b33516295.jpg"},{"id":107,"name":"Family Friendly","slug":"family-friendly","language":"eng","games_count":6649,"image_background":"https://media.rawg.io/media/games/a87/a8743bdee8627c55bb9f2f01b9136ac1.jpg"},{"id":88,"name":"Cute","slug":"cute","language":"eng","games_count":31798,"image_background":"https://media.rawg.io/media/games/276/2769b1982cd132a60c69dc5d574445fa.jpg"},{"id":37797,"name":"true exclusive","slug":"true-exclusive","language":"eng","games_count":3986,"image_background":"https://media.rawg.io/media/games/560/56056a71c74f751552c9baedebf8f317.jpg"},{"id":229,"name":"3D Platformer","slug":"3d-platformer","language":"eng","games_count":9534,"image_background":"https://media.rawg.io/media/games/a3e/a3ea71c18e81d54ebaf982dadb9a8738.jpg"},{"id":284,"name":"Cult Classic","slug":"cult-classic","language":"eng","games_count":984,"image_background":"https://media.rawg.io/media/games/0a3/0a3a4838159eaf02f7b3d9a805d516d3.jpg"},{"id":1325,"name":"kids","slug":"kids","language":"eng","games_count":5188,"image_background":"https://media.rawg.io/media/screenshots/b3c/b3c672e0d9094baf91ef619002bbe82b.jpg"}],"esrb_rating":{"id":2,"name":"Everyone 10+","slug":"everyone-10-plus"},"short_screenshots":[{"id":-1,"image":"https://media.rawg.io/media/games/267/267bd0dbc496f52692487d07d014c061.jpg"},{"id":1865433,"image":"https://media.rawg.io/media/screenshots/a38/a38e8c2161eb6c3c233b0488a3c2d5f1.jpg"},{"id":268122,"image":"https://media.rawg.io/media/screenshots/ff8/ff80f35e3301fa9c0027d9f021c24340.jpg"},{"id":268123,"image":"https://media.rawg.io/media/screenshots/82c/82ce6aa4915756bd39cd1e6a02e17a77.jpg"},{"id":268124,"image":"https://media.rawg.io/media/screenshots/28b/28bb29070fce9fc1e45900aaebe83b2a.jpg"},{"id":268125,"image":"https://media.rawg.io/media/screenshots/014/014e53bf0f33afc3a0d0fcfaa2715f73.jpg"},{"id":268126,"image":"https://media.rawg.io/media/screenshots/02d/02d7425ce977a7a556beadbac4a2ae63.jpg"}]},{"id":27036,"slug":"super-mario-galaxy-2","name":"Super Mario Galaxy 2","released":"2010-05-23","tba":false,"background_image":"https://media.rawg.io/media/games/4e9/4e928ff4b4e3c3f5acfda38b98a4cf65.jpg","rating":4.36,"rating_top":5,"ratings":[{"id":5,"title":"exceptional","count":260,"percent":64.52},{"id":4,"title":"recommended","count":89,"percent":22.08},{"id":1,"title":"skip","count":31,"percent":7.69},{"id":3,"title":"meh","count":23,"percent":5.71}],"ratings_count":396,"reviews_text_count":5,"added":911,"added_by_status":{"yet":79,"owned":203,"beaten":395,"toplay":136,"dropped":83,"playing":15},"metacritic":97,"playtime":18,"suggestions_count":343,"updated":"2024-01-17T21:16:57","user_game":null,"reviews_count":403,"saturated_color":"0f0f0f","dominant_color":"0f0f0f","platforms":[{"platform":{"id":11,"name":"Wii","slug":"wii","image":null,"year_end":null,"year_start":null,"games_count":2232,"image_background":"https://media.rawg.io/media/games/341/3413d7275fb1e919f00a925df8288b77.jpg"},"released_at":"2010-05-23","requirements_en":null,"requirements_ru":null},{"platform":{"id":10,"name":"Wii U","slug":"wii-u","image":null,"year_end":null,"year_start":null,"games_count":1128,"image_background":"https://media.rawg.io/media/games/e4f/e4fb3fd188f61fabec48dca22e6ef28a.jpg"},"released_at":"2010-05-23","requirements_en":null,"requirements_ru":null}],"parent_platforms":[{"platform":{"id":7,"name":"Nintendo","slug":"nintendo"}}],"genres":[{"id":83,"name":"Platformer","slug":"platformer","games_count":100745,"image_background":"https://media.rawg.io/media/games/04a/04a7e7e185fb51493bdcbe1693a8b3dc.jpg"}],"stores":[{"id":31677,"store":{"id":6,"name":"Nintendo Store","slug":"nintendo","domain":"nintendo.com","games_count":8946,"image_background":"https://media.rawg.io/media/games/f99/f9979698c43fd84c3ab69280576dd3af.jpg"}}],"clip":null,"tags":[{"id":1743,"name":"collect","slug":"collect","language":"eng","games_count":8063,"image_background":"https://media.rawg.io/media/screenshots/c09/c09916af3e234e2b4ca2017d0a4c4ff4.jpg"},{"id":500,"name":"Solo","slug":"solo","language":"eng","games_count":1627,"image_background":"https://media.rawg.io/media/games/431/4317e294e88e4c9d77327693b15f499a.jpg"},{"id":6903,"name":"galaxy","slug":"galaxy","language":"eng","games_count":1192,"image_background":"https://media.rawg.io/media/games/a81/a8174eaeb351d922f7dafea32878bd0d.jpg"},{"id":3397,"name":"light","slug":"light","language":"eng","games_count":1739,"image_background":"https://media.rawg.io/media/screenshots/ec5/ec5d34a071eefffd01c30020007134be.jpeg"},{"id":2006,"name":"castle","slug":"castle","language":"eng","games_count":1519,"image_background":"https://media.rawg.io/media/games/a6c/a6c68aba6208a3b8a26cf2cdc41a5e0c.jpg"},{"id":1593,"name":"Gravity","slug":"gravity","language":"eng","games_count":3293,"image_background":"https://media.rawg.io/media/games/839/83924d4b0be37f607d14a5c463dc0e47.jpg"},{"id":1156,"name":"princess","slug":"princess","language":"eng","games_count":1268,"image_background":"https://media.rawg.io/media/games/158/158e3d88feea5b59bd8c48205a37e341.jpg"},{"id":1598,"name":"mario","slug":"mario","language":"eng","games_count":1299,"image_background":"https://media.rawg.io/media/games/4e9/4e928ff4b4e3c3f5acfda38b98a4cf65.jpg"},{"id":1925,"name":"baby","slug":"baby","language":"eng","games_count":1419,"image_background":"https://media.rawg.io/media/screenshots/0db/0db22c610b411ffdd2c390cbfdcb6c79.jpg"}],"esrb_rating":{"id":1,"name":"Everyone","slug":"everyone"},"short_screenshots":[{"id":-1,"image":"https://media.rawg.io/media/games/4e9/4e928ff4b4e3c3f5acfda38b98a4cf65.jpg"},{"id":259592,"image":"https://media.rawg.io/media/screenshots/018/01820c00321809689719810909597a8a.jpg"},{"id":259593,"image":"https://media.rawg.io/media/screenshots/c69/c6962ca0448e505f4a3f7fee40b0763c.jpg"},{"id":259594,"image":"https://media.rawg.io/media/screenshots/5c8/5c86ddad098f86c728af5a60ee546cd3.jpg"},{"id":259595,"image":"https://media.rawg.io/media/screenshots/217/2175824497a01738be96b7a41f609b50.jpg"},{"id":259596,"image":"https://media.rawg.io/media/screenshots/d38/d38ab46e6caf82664a8a643c114f4823.jpg"},{"id":259597,"image":"https://media.rawg.io/media/screenshots/655/655ea00123daccdf867f3682b8e2848e.jpg"}]},{"id":27024,"slug":"super-mario-galaxy","name":"Super Mario Galaxy","released":"2007-11-01","tba":false,"background_image":"https://media.rawg.io/media/games/936/936f0ffac0b3c9f5c8d185f610ed2631.jpg","rating":4.38,"rating_top":5,"ratings":[{"id":5,"title":"exceptional","count":478,"percent":64.25},{"id":4,"title":"recommended","count":171,"percent":22.98},{"id":1,"title":"skip","count":51,"percent":6.85},{"id":3,"title":"meh","count":44,"percent":5.91}],"ratings_count":737,"reviews_text_count":6,"added":1480,"added_by_status":{"yet":101,"owned":364,"beaten":691,"toplay":147,"dropped":133,"playing":44},"metacritic":97,"playtime":28,"suggestions_count":332,"updated":"2024-01-13T08:43:54","user_game":null,"reviews_count":744,"saturated_color":"0f0f0f","dominant_color":"0f0f0f","platforms":[{"platform":{"id":11,"name":"Wii","slug":"wii","image":null,"year_end":null,"year_start":null,"games_count":2232,"image_background":"https://media.rawg.io/media/games/341/3413d7275fb1e919f00a925df8288b77.jpg"},"released_at":"2007-11-01","requirements_en":null,"requirements_ru":null}],"parent_platforms":[{"platform":{"id":7,"name":"Nintendo","slug":"nintendo"}}],"genres":[{"id":83,"name":"Platformer","slug":"platformer","games_count":100745,"image_background":"https://media.rawg.io/media/games/04a/04a7e7e185fb51493bdcbe1693a8b3dc.jpg"}],"stores":[{"id":31662,"store":{"id":6,"name":"Nintendo Store","slug":"nintendo","domain":"nintendo.com","games_count":8946,"image_background":"https://media.rawg.io/media/games/f99/f9979698c43fd84c3ab69280576dd3af.jpg"}}],"clip":null,"tags":[{"id":5816,"name":"console","slug":"console","language":"eng","games_count":1388,"image_background":"https://media.rawg.io/media/games/819/819cbc1d24837166b24299f5c8b68e07.jpg"},{"id":1105,"name":"planet","slug":"planet","language":"eng","games_count":3001,"image_background":"https://media.rawg.io/media/games/c9f/c9fbbde8236fbefa330658166eba8419.jpg"},{"id":1593,"name":"Gravity","slug":"gravity","language":"eng","games_count":3293,"image_background":"https://media.rawg.io/media/games/839/83924d4b0be37f607d14a5c463dc0e47.jpg"},{"id":731,"name":"NES","slug":"nes","language":"eng","games_count":1335,"image_background":"https://media.rawg.io/media/screenshots/fe7/fe74794fc0292a9fbcda2b1d0c47f0ec.jpg"},{"id":1598,"name":"mario","slug":"mario","language":"eng","games_count":1299,"image_background":"https://media.rawg.io/media/games/4e9/4e928ff4b4e3c3f5acfda38b98a4cf65.jpg"}],"esrb_rating":{"id":1,"name":"Everyone","slug":"everyone"},"short_screenshots":[{"id":-1,"image":"https://media.rawg.io/media/games/936/936f0ffac0b3c9f5c8d185f610ed2631.jpg"},{"id":259488,"image":"https://media.rawg.io/media/screenshots/83f/83f80635904e97cfc4f13708723a058c.jpg"},{"id":259489,"image":"https://media.rawg.io/media/screenshots/95e/95ed0d6e674b7901cde508c16c5947ad.jpg"},{"id":259490,"image":"https://media.rawg.io/media/screenshots/78f/78f185aeb72e8be1bb80962653a1fc58.jpg"},{"id":259491,"image":"https://media.rawg.io/media/screenshots/8a8/8a8368744220217f3702629bb03d15f9.jpg"},{"id":265320,"image":"https://media.rawg.io/media/screenshots/7b5/7b504c79196501e7afa776492dc5d9fb.jpg"},{"id":265321,"image":"https://media.rawg.io/media/screenshots/f69/f69710b403ca2a72f5273137cd1fa538.jpg"}]},{"id":22511,"slug":"the-legend-of-zelda-breath-of-the-wild","name":"The Legend of Zelda: Breath of the Wild","released":"2017-03-03","tba":false,"background_image":"https://media.rawg.io/media/games/cc1/cc196a5ad763955d6532cdba236f730c.jpg","rating":4.54,"rating_top":5,"ratings":[{"id":5,"title":"exceptional","count":2154,"percent":73.34},{"id":4,"title":"recommended","count":485,"percent":16.51},{"id":3,"title":"meh","count":157,"percent":5.35},{"id":1,"title":"skip","count":141,"percent":4.8}],"ratings_count":2879,"reviews_text_count":44,"added":5715,"added_by_status":{"yet":331,"owned":1315,"beaten":2187,"toplay":742,"dropped":448,"playing":692},"metacritic":97,"playtime":121,"suggestions_count":304,"updated":"2024-01-23T12:13:46","user_game":null,"reviews_count":2937,"saturated_color":"0f0f0f","dominant_color":"0f0f0f","platforms":[{"platform":{"id":7,"name":"Nintendo Switch","slug":"nintendo-switch","image":null,"year_end":null,"year_start":null,"games_count":5380,"image_background":"https://media.rawg.io/media/games/f99/f9979698c43fd84c3ab69280576dd3af.jpg"},"released_at":"2017-03-03","requirements_en":null,"requirements_ru":null},{"platform":{"id":10,"name":"Wii U","slug":"wii-u","image":null,"year_end":null,"year_start":null,"games_count":1128,"image_background":"https://media.rawg.io/media/games/e4f/e4fb3fd188f61fabec48dca22e6ef28a.jpg"},"released_at":"2017-03-03","requirements_en":null,"requirements_ru":null}],"parent_platforms":[{"platform":{"id":7,"name":"Nintendo","slug":"nintendo"}}],"genres":[{"id":4,"name":"Action","slug":"action","games_count":177743,"image_background":"https://media.rawg.io/media/games/49c/49c3dfa4ce2f6f140cc4825868e858cb.jpg"},{"id":3,"name":"Adventure","slug":"adventure","games_count":137364,"image_background":"https://media.rawg.io/media/games/562/562553814dd54e001a541e4ee83a591c.jpg"},{"id":5,"name":"RPG","slug":"role-playing-games-rpg","games_count":54782,"image_background":"https://media.rawg.io/media/games/1f4/1f47a270b8f241e4676b14d39ec620f7.jpg"}],"stores":[{"id":31384,"store":{"id":6,"name":"Nintendo Store","slug":"nintendo","domain":"nintendo.com","games_count":8946,"image_background":"https://media.rawg.io/media/games/f99/f9979698c43fd84c3ab69280576dd3af.jpg"}}],"clip":null,"tags":[{"id":24,"name":"RPG","slug":"rpg","language":"eng","games_count":19541,"image_background":"https://media.rawg.io/media/games/b45/b45575f34285f2c4479c9a5f719d972e.jpg"},{"id":36,"name":"Open World","slug":"open-world","language":"eng","games_count":7033,"image_background":"https://media.rawg.io/media/games/20a/20aa03a10cda45239fe22d035c0ebe64.jpg"},{"id":37,"name":"Sandbox","slug":"sandbox","language":"eng","games_count":6532,"image_background":"https://media.rawg.io/media/games/20a/20aa03a10cda45239fe22d035c0ebe64.jpg"},{"id":69,"name":"Action-Adventure","slug":"action-adventure","language":"eng","games_count":15262,"image_background":"https://media.rawg.io/media/games/275/2759da6fcaa8f81f21800926168c85f6.jpg"},{"id":37796,"name":"exclusive","slug":"exclusive","language":"eng","games_count":4500,"image_background":"https://media.rawg.io/media/games/f0e/f0e050dc774d4ae3afced76b33516295.jpg"}],"esrb_rating":{"id":2,"name":"Everyone 10+","slug":"everyone-10-plus"},"short_screenshots":[{"id":-1,"image":"https://media.rawg.io/media/games/cc1/cc196a5ad763955d6532cdba236f730c.jpg"},{"id":806574,"image":"https://media.rawg.io/media/screenshots/3c4/3c4a8f6b1994def75e73e1cb64624e7f.jpg"},{"id":806575,"image":"https://media.rawg.io/media/screenshots/8f5/8f5d4264b12090bb7aa5626fcfb5be18.jpg"},{"id":806576,"image":"https://media.rawg.io/media/screenshots/b77/b771adc0585c655f8a747d3160e5325a.jpg"},{"id":806577,"image":"https://media.rawg.io/media/screenshots/ef7/ef7d89471e5c0dc5553c249b2c34d9cd.jpg"},{"id":806578,"image":"https://media.rawg.io/media/screenshots/1e5/1e58e8a064da6906f09dba1edb3fdea6.jpg"},{"id":806579,"image":"https://media.rawg.io/media/screenshots/bef/bef44f5547b97d44c5e14f8773f9876c.jpg"}]},{"id":401808,"slug":"half-life-2-update","name":"Half-Life 2: Update","released":"2015-03-27","tba":false,"background_image":"https://media.rawg.io/media/screenshots/bb7/bb7463d103dc40f6f3a3c9ac3b4b11a5.jpg","rating":4.14,"rating_top":5,"ratings":[{"id":5,"title":"exceptional","count":61,"percent":50.83},{"id":4,"title":"recommended","count":37,"percent":30.83},{"id":3,"title":"meh","count":11,"percent":9.17},{"id":1,"title":"skip","count":11,"percent":9.17}],"ratings_count":120,"reviews_text_count":0,"added":1791,"added_by_status":{"yet":53,"owned":1604,"beaten":106,"toplay":4,"dropped":22,"playing":2},"metacritic":96,"playtime":1,"suggestions_count":523,"updated":"2023-12-13T00:49:23","user_game":null,"reviews_count":120,"saturated_color":"0f0f0f","dominant_color":"0f0f0f","platforms":[{"platform":{"id":4,"name":"PC","slug":"pc","image":null,"year_end":null,"year_start":null,"games_count":524416,"image_background":"https://media.rawg.io/media/games/120/1201a40e4364557b124392ee50317b99.jpg"},"released_at":"2015-03-27","requirements_en":null,"requirements_ru":null}],"parent_platforms":[{"platform":{"id":1,"name":"PC","slug":"pc"}}],"genres":[{"id":2,"name":"Shooter","slug":"shooter","games_count":59432,"image_background":"https://media.rawg.io/media/games/34b/34b1f1850a1c06fd971bc6ab3ac0ce0e.jpg"}],"stores":[{"id":391702,"store":{"id":1,"name":"Steam","slug":"steam","domain":"store.steampowered.com","games_count":87632,"image_background":"https://media.rawg.io/media/games/490/49016e06ae2103881ff6373248843069.jpg"}}],"clip":null,"tags":[],"esrb_rating":{"id":4,"name":"Mature","slug":"mature"},"short_screenshots":[{"id":-1,"image":"https://media.rawg.io/media/screenshots/bb7/bb7463d103dc40f6f3a3c9ac3b4b11a5.jpg"},{"id":2264517,"image":"https://media.rawg.io/media/screenshots/ac5/ac56b6302f03a34ec8db40ae63033d0c.jpg"},{"id":2264518,"image":"https://media.rawg.io/media/screenshots/aa5/aa58994169eeb69ce95b16c170a91733.jpg"},{"id":2264519,"image":"https://media.rawg.io/media/screenshots/957/957e11a02cbc0500b3264a1a0773511a.jpg"},{"id":2264520,"image":"https://media.rawg.io/media/screenshots/39b/39b6ea60eabc0b2d6318b5c65d3c751b.jpg"},{"id":2264521,"image":"https://media.rawg.io/media/screenshots/19c/19cec8649b11d718e37e79ed6c736627.jpg"},{"id":2264522,"image":"https://media.rawg.io/media/screenshots/832/8323b65359639b20f07d9e1bc405c6ff.jpg"}]},{"id":327239,"slug":"the-legend-of-zelda-breath-of-the-wild-sequel","name":"The Legend of Zelda: Tears of the Kingdom","released":"2023-05-12","tba":false,"background_image":"https://media.rawg.io/media/games/556/55684bfd048706f4266d331d70050b37.jpg","rating":4.48,"rating_top":5,"ratings":[{"id":5,"title":"exceptional","count":228,"percent":72.38},{"id":4,"title":"recommended","count":55,"percent":17.46},{"id":1,"title":"skip","count":23,"percent":7.3},{"id":3,"title":"meh","count":9,"percent":2.86}],"ratings_count":305,"reviews_text_count":9,"added":1312,"added_by_status":{"yet":143,"owned":196,"beaten":194,"toplay":562,"dropped":51,"playing":166},"metacritic":96,"playtime":0,"suggestions_count":469,"updated":"2024-01-21T00:42:27","user_game":null,"reviews_count":315,"saturated_color":"0f0f0f","dominant_color":"0f0f0f","platforms":[{"platform":{"id":7,"name":"Nintendo Switch","slug":"nintendo-switch","image":null,"year_end":null,"year_start":null,"games_count":5380,"image_background":"https://media.rawg.io/media/games/f99/f9979698c43fd84c3ab69280576dd3af.jpg"},"released_at":"2023-05-12","requirements_en":null,"requirements_ru":null}],"parent_platforms":[{"platform":{"id":7,"name":"Nintendo","slug":"nintendo"}}],"genres":[{"id":4,"name":"Action","slug":"action","games_count":177742,"image_background":"https://media.rawg.io/media/games/310/3106b0e012271c5ffb16497b070be739.jpg"},{"id":3,"name":"Adventure","slug":"adventure","games_count":137363,"image_background":"https://media.rawg.io/media/games/995/9951d9d55323d08967640f7b9ab3e342.jpg"}],"stores":[{"id":954190,"store":{"id":6,"name":"Nintendo Store","slug":"nintendo","domain":"nintendo.com","games_count":8946,"image_background":"https://media.rawg.io/media/games/f99/f9979698c43fd84c3ab69280576dd3af.jpg"}}],"clip":null,"tags":[{"id":31,"name":"Singleplayer","slug":"singleplayer","language":"eng","games_count":216849,"image_background":"https://media.rawg.io/media/games/4a0/4a0a1316102366260e6f38fd2a9cfdce.jpg"},{"id":24,"name":"RPG","slug":"rpg","language":"eng","games_count":19541,"image_background":"https://media.rawg.io/media/games/b45/b45575f34285f2c4479c9a5f719d972e.jpg"},{"id":36,"name":"Open World","slug":"open-world","language":"eng","games_count":7033,"image_background":"https://media.rawg.io/media/games/20a/20aa03a10cda45239fe22d035c0ebe64.jpg"},{"id":37,"name":"Sandbox","slug":"sandbox","language":"eng","games_count":6532,"image_background":"https://media.rawg.io/media/games/20a/20aa03a10cda45239fe22d035c0ebe64.jpg"},{"id":37796,"name":"exclusive","slug":"exclusive","language":"eng","games_count":4500,"image_background":"https://media.rawg.io/media/games/f0e/f0e050dc774d4ae3afced76b33516295.jpg"},{"id":425,"name":"Single player only","slug":"single-player-only","language":"eng","games_count":31,"image_background":"https://media.rawg.io/media/screenshots/3eb/3eb918422509a15405e723cf18cddc34.jpg"},{"id":867,"name":"zelda","slug":"zelda","language":"eng","games_count":452,"image_background":"https://media.rawg.io/media/screenshots/b23/b23b3b0f25b10123c0338cf9f5c8bc12.jpg"}],"esrb_rating":{"id":2,"name":"Everyone 10+","slug":"everyone-10-plus"},"short_screenshots":[{"id":-1,"image":"https://media.rawg.io/media/games/556/55684bfd048706f4266d331d70050b37.jpg"},{"id":1961492,"image":"https://media.rawg.io/media/screenshots/51f/51f7928a2630fc4bbb3dac59b8f31448.jpg"},{"id":1961493,"image":"https://media.rawg.io/media/screenshots/104/10431d15726ed2593401cc70e2115a82.jpg"},{"id":1961494,"image":"https://media.rawg.io/media/screenshots/c0d/c0dafd15ec182acab8f5879665eaa642.jpg"},{"id":1961495,"image":"https://media.rawg.io/media/screenshots/725/725dbbf72f15a32f418a42d2e8ac8b25.jpg"},{"id":1961496,"image":"https://media.rawg.io/media/screenshots/c63/c63fda6df2574a7d071f96082438e820.jpg"},{"id":2897101,"image":"https://media.rawg.io/media/screenshots/c92/c92c2acf519b3dc613c0f0085cc34b34.jpg"}]},{"id":57842,"slug":"tekken-3","name":"Tekken 3","released":"1997-03-20","tba":false,"background_image":"https://media.rawg.io/media/games/4aa/4aa1440932f4a12d9d0ea70a5e2164f6.jpg","rating":4.4,"rating_top":5,"ratings":[{"id":5,"title":"exceptional","count":290,"percent":55.77},{"id":4,"title":"recommended","count":182,"percent":35},{"id":3,"title":"meh","count":30,"percent":5.77},{"id":1,"title":"skip","count":18,"percent":3.46}],"ratings_count":519,"reviews_text_count":1,"added":872,"added_by_status":{"yet":13,"owned":184,"beaten":477,"toplay":25,"dropped":171,"playing":2},"metacritic":96,"playtime":1,"suggestions_count":426,"updated":"2024-01-23T13:23:08","user_game":null,"reviews_count":520,"saturated_color":"0f0f0f","dominant_color":"0f0f0f","platforms":[{"platform":{"id":27,"name":"PlayStation","slug":"playstation1","image":null,"year_end":null,"year_start":null,"games_count":1660,"image_background":"https://media.rawg.io/media/games/837/837a609b0584db5d03534c8e767861b1.jpg"},"released_at":"1997-03-20","requirements_en":null,"requirements_ru":null}],"parent_platforms":[{"platform":{"id":2,"name":"PlayStation","slug":"playstation"}}],"genres":[{"id":6,"name":"Fighting","slug":"fighting","games_count":11746,"image_background":"https://media.rawg.io/media/games/234/23410661770ae13eac11066980834367.jpg"}],"stores":[],"clip":null,"tags":[{"id":31,"name":"Singleplayer","slug":"singleplayer","language":"eng","games_count":216849,"image_background":"https://media.rawg.io/media/games/4a0/4a0a1316102366260e6f38fd2a9cfdce.jpg"},{"id":7,"name":"Multiplayer","slug":"multiplayer","language":"eng","games_count":36937,"image_background":"https://media.rawg.io/media/games/587/587588c64afbff80e6f444eb2e46f9da.jpg"},{"id":37796,"name":"exclusive","slug":"exclusive","language":"eng","games_count":4500,"image_background":"https://media.rawg.io/media/games/f0e/f0e050dc774d4ae3afced76b33516295.jpg"}],"esrb_rating":null,"short_screenshots":[{"id":-1,"image":"https://media.rawg.io/media/games/4aa/4aa1440932f4a12d9d0ea70a5e2164f6.jpg"},{"id":1643596,"image":"https://media.rawg.io/media/screenshots/78b/78bc6da0a5957f2013fff93b698b7cb6_OHGlt5j.jpg"},{"id":1643597,"image":"https://media.rawg.io/media/screenshots/227/227b8bb79a9c242381bde640bc19647d.jpg"},{"id":1643598,"image":"https://media.rawg.io/media/screenshots/168/1686c77d1759c0d6749cdf8b5726bd45.jpg"},{"id":1643599,"image":"https://media.rawg.io/media/screenshots/774/774629dfbbe67ce0b7c2c0f960a5ec7b.jpg"}]},{"id":54403,"slug":"goldeneye-007-1997","name":"GoldenEye 007 (1997)","released":"1997-08-23","tba":false,"background_image":"https://media.rawg.io/media/games/5a1/5a145fe3002fc988140f7f00edcb9715.jpg","rating":4.37,"rating_top":5,"ratings":[{"id":5,"title":"exceptional","count":101,"percent":51.27},{"id":4,"title":"recommended","count":78,"percent":39.59},{"id":3,"title":"meh","count":13,"percent":6.6},{"id":1,"title":"skip","count":5,"percent":2.54}],"ratings_count":194,"reviews_text_count":3,"added":422,"added_by_status":{"yet":29,"owned":103,"beaten":166,"toplay":39,"dropped":80,"playing":5},"metacritic":96,"playtime":0,"suggestions_count":256,"updated":"2024-01-17T14:09:28","user_game":null,"reviews_count":197,"saturated_color":"0f0f0f","dominant_color":"0f0f0f","platforms":[{"platform":{"id":83,"name":"Nintendo 64","slug":"nintendo-64","image":null,"year_end":null,"year_start":null,"games_count":363,"image_background":"https://media.rawg.io/media/screenshots/4cf/4cf1e2b4cd701605225fb443d5e84f77.jpg"},"released_at":"1997-08-23","requirements_en":null,"requirements_ru":null}],"parent_platforms":[{"platform":{"id":7,"name":"Nintendo","slug":"nintendo"}}],"genres":[{"id":2,"name":"Shooter","slug":"shooter","games_count":59432,"image_background":"https://media.rawg.io/media/games/34b/34b1f1850a1c06fd971bc6ab3ac0ce0e.jpg"}],"stores":[],"clip":null,"tags":[{"id":31,"name":"Singleplayer","slug":"singleplayer","language":"eng","games_count":216849,"image_background":"https://media.rawg.io/media/games/4a0/4a0a1316102366260e6f38fd2a9cfdce.jpg"},{"id":7,"name":"Multiplayer","slug":"multiplayer","language":"eng","games_count":36937,"image_background":"https://media.rawg.io/media/games/587/587588c64afbff80e6f444eb2e46f9da.jpg"},{"id":37796,"name":"exclusive","slug":"exclusive","language":"eng","games_count":4500,"image_background":"https://media.rawg.io/media/games/f0e/f0e050dc774d4ae3afced76b33516295.jpg"},{"id":37797,"name":"true exclusive","slug":"true-exclusive","language":"eng","games_count":3986,"image_background":"https://media.rawg.io/media/games/560/56056a71c74f751552c9baedebf8f317.jpg"}],"esrb_rating":null,"short_screenshots":[{"id":-1,"image":"https://media.rawg.io/media/games/5a1/5a145fe3002fc988140f7f00edcb9715.jpg"},{"id":740715,"image":"https://media.rawg.io/media/screenshots/a3a/a3a0047c031ef5ebd6b73f3990e4152e.jpg"},{"id":740716,"image":"https://media.rawg.io/media/screenshots/a2c/a2c9645dd83faafdde6d1c4f9e01bfcf.jpg"},{"id":740717,"image":"https://media.rawg.io/media/screenshots/4cc/4cca1b529a5c2cd7ae248406092bcdbf.jpg"},{"id":740718,"image":"https://media.rawg.io/media/screenshots/58d/58d5673cecfd387f3f16f312eb0531a1.jpg"},{"id":740719,"image":"https://media.rawg.io/media/screenshots/242/242bc99092b1ea144c1a8454d2ad9773.jpg"},{"id":740720,"image":"https://media.rawg.io/media/screenshots/079/0799419f0c905e4cba6043ce44375032.jpg"}]},{"id":52995,"slug":"gran-turismo","name":"Gran Turismo","released":"1997-12-22","tba":false,"background_image":"https://media.rawg.io/media/games/5ac/5ac568dcf73aedba140bcca2a8a5eb09.jpg","rating":4.33,"rating_top":4,"ratings":[{"id":4,"title":"recommended","count":48,"percent":46.15},{"id":5,"title":"exceptional","count":46,"percent":44.23},{"id":3,"title":"meh","count":9,"percent":8.65},{"id":1,"title":"skip","count":1,"percent":0.96}],"ratings_count":103,"reviews_text_count":1,"added":241,"added_by_status":{"yet":10,"owned":54,"beaten":83,"toplay":12,"dropped":79,"playing":3},"metacritic":96,"playtime":0,"suggestions_count":303,"updated":"2023-11-08T06:53:36","user_game":null,"reviews_count":104,"saturated_color":"0f0f0f","dominant_color":"0f0f0f","platforms":[{"platform":{"id":27,"name":"PlayStation","slug":"playstation1","image":null,"year_end":null,"year_start":null,"games_count":1660,"image_background":"https://media.rawg.io/media/games/837/837a609b0584db5d03534c8e767861b1.jpg"},"released_at":"1997-12-22","requirements_en":null,"requirements_ru":null}],"parent_platforms":[{"platform":{"id":2,"name":"PlayStation","slug":"playstation"}}],"genres":[{"id":1,"name":"Racing","slug":"racing","games_count":24516,"image_background":"https://media.rawg.io/media/games/a01/a01b34c722ceec784817381eb1824fa5.jpg"}],"stores":[],"clip":null,"tags":[{"id":31,"name":"Singleplayer","slug":"singleplayer","language":"eng","games_count":216849,"image_background":"https://media.rawg.io/media/games/4a0/4a0a1316102366260e6f38fd2a9cfdce.jpg"},{"id":7,"name":"Multiplayer","slug":"multiplayer","language":"eng","games_count":36937,"image_background":"https://media.rawg.io/media/games/587/587588c64afbff80e6f444eb2e46f9da.jpg"},{"id":37796,"name":"exclusive","slug":"exclusive","language":"eng","games_count":4500,"image_background":"https://media.rawg.io/media/games/f0e/f0e050dc774d4ae3afced76b33516295.jpg"},{"id":37797,"name":"true exclusive","slug":"true-exclusive","language":"eng","games_count":3986,"image_background":"https://media.rawg.io/media/games/560/56056a71c74f751552c9baedebf8f317.jpg"}],"esrb_rating":null,"short_screenshots":[{"id":-1,"image":"https://media.rawg.io/media/games/5ac/5ac568dcf73aedba140bcca2a8a5eb09.jpg"},{"id":729929,"image":"https://media.rawg.io/media/screenshots/0fb/0fb1caa87b08994d7ec7ef18fb5166d6.jpg"},{"id":729930,"image":"https://media.rawg.io/media/screenshots/b6a/b6af6d5bdf1f662613158b9d7e7ee4ce.jpg"},{"id":729931,"image":"https://media.rawg.io/media/screenshots/810/810fe64f184b9f2e956460b4fd2945a0.jpg"},{"id":729932,"image":"https://media.rawg.io/media/screenshots/48e/48ece00be2339fdda6ef042954428ac2.jpg"},{"id":729933,"image":"https://media.rawg.io/media/screenshots/7a0/7a0db606ca8702c3df8289ca69afcb01.jpg"},{"id":729934,"image":"https://media.rawg.io/media/screenshots/aaf/aafdb2667920be307b95ada06681fc19.jpg"}]},{"id":52370,"slug":"metal-gear-solid-2-sons-of-liberty","name":"Metal Gear Solid 2: Sons of Liberty","released":"2001-11-12","tba":false,"background_image":"https://media.rawg.io/media/games/0f1/0f105a3d3ba6225269c4a08b43ecbb73.jpg","rating":4.35,"rating_top":5,"ratings":[{"id":5,"title":"exceptional","count":328,"percent":62.6},{"id":4,"title":"recommended","count":132,"percent":25.19},{"id":1,"title":"skip","count":39,"percent":7.44},{"id":3,"title":"meh","count":25,"percent":4.77}],"ratings_count":518,"reviews_text_count":5,"added":1062,"added_by_status":{"yet":86,"owned":233,"beaten":539,"toplay":129,"dropped":61,"playing":14},"metacritic":96,"playtime":12,"suggestions_count":174,"updated":"2024-01-08T15:36:57","user_game":null,"reviews_count":524,"saturated_color":"0f0f0f","dominant_color":"0f0f0f","platforms":[{"platform":{"id":15,"name":"PlayStation 2","slug":"playstation2","image":null,"year_end":null,"year_start":null,"games_count":2020,"image_background":"https://media.rawg.io/media/games/2ee/2eef5ed5e82c28d1299ecc2a0e60f2cb.jpg"},"released_at":"2001-11-12","requirements_en":null,"requirements_ru":null},{"platform":{"id":16,"name":"PlayStation 3","slug":"playstation3","image":null,"year_end":null,"year_start":null,"games_count":3161,"image_background":"https://media.rawg.io/media/games/d69/d69810315bd7e226ea2d21f9156af629.jpg"},"released_at":"2001-11-12","requirements_en":null,"requirements_ru":null},{"platform":{"id":19,"name":"PS Vita","slug":"ps-vita","image":null,"year_end":null,"year_start":null,"games_count":1445,"image_background":"https://media.rawg.io/media/games/9fa/9fa63622543e5d4f6d99aa9d73b043de.jpg"},"released_at":"2001-11-12","requirements_en":null,"requirements_ru":null},{"platform":{"id":14,"name":"Xbox 360","slug":"xbox360","image":null,"year_end":null,"year_start":null,"games_count":2787,"image_background":"https://media.rawg.io/media/games/15c/15c95a4915f88a3e89c821526afe05fc.jpg"},"released_at":"2001-11-12","requirements_en":null,"requirements_ru":null},{"platform":{"id":80,"name":"Xbox","slug":"xbox-old","image":null,"year_end":null,"year_start":null,"games_count":735,"image_background":"https://media.rawg.io/media/games/99b/99b39612e864d6ddfdb2c407fd9010a1.jpg"},"released_at":"2001-11-12","requirements_en":null,"requirements_ru":null}],"parent_platforms":[{"platform":{"id":2,"name":"PlayStation","slug":"playstation"}},{"platform":{"id":3,"name":"Xbox","slug":"xbox"}}],"genres":[{"id":4,"name":"Action","slug":"action","games_count":177743,"image_background":"https://media.rawg.io/media/games/49c/49c3dfa4ce2f6f140cc4825868e858cb.jpg"},{"id":2,"name":"Shooter","slug":"shooter","games_count":59432,"image_background":"https://media.rawg.io/media/games/34b/34b1f1850a1c06fd971bc6ab3ac0ce0e.jpg"},{"id":3,"name":"Adventure","slug":"adventure","games_count":137364,"image_background":"https://media.rawg.io/media/games/562/562553814dd54e001a541e4ee83a591c.jpg"}],"stores":[{"id":49003,"store":{"id":3,"name":"PlayStation Store","slug":"playstation-store","domain":"store.playstation.com","games_count":7878,"image_background":"https://media.rawg.io/media/games/157/15742f2f67eacff546738e1ab5c19d20.jpg"}},{"id":277746,"store":{"id":7,"name":"Xbox 360 Store","slug":"xbox360","domain":"marketplace.xbox.com","games_count":1912,"image_background":"https://media.rawg.io/media/games/960/960b601d9541cec776c5fa42a00bf6c4.jpg"}}],"clip":null,"tags":[{"id":13,"name":"Atmospheric","slug":"atmospheric","language":"eng","games_count":31740,"image_background":"https://media.rawg.io/media/games/490/49016e06ae2103881ff6373248843069.jpg"},{"id":15,"name":"Stealth","slug":"stealth","language":"eng","games_count":6064,"image_background":"https://media.rawg.io/media/games/7ac/7aca7ccf0e70cd0974cb899ab9e5158e.jpg"},{"id":69,"name":"Action-Adventure","slug":"action-adventure","language":"eng","games_count":15262,"image_background":"https://media.rawg.io/media/games/275/2759da6fcaa8f81f21800926168c85f6.jpg"}],"esrb_rating":{"id":4,"name":"Mature","slug":"mature"},"short_screenshots":[{"id":-1,"image":"https://media.rawg.io/media/games/0f1/0f105a3d3ba6225269c4a08b43ecbb73.jpg"},{"id":725541,"image":"https://media.rawg.io/media/screenshots/b41/b41d266e0df00a709033b5df801951f4.jpg"},{"id":725542,"image":"https://media.rawg.io/media/screenshots/b4a/b4a112017533a5d916747f93fc799459.jpg"},{"id":725543,"image":"https://media.rawg.io/media/screenshots/f3b/f3b44dbfc5738efacccd627a9ff83861.jpg"},{"id":725544,"image":"https://media.rawg.io/media/screenshots/2e0/2e0941b4fb3c9c604b5858c3675d1bc5.jpg"},{"id":725545,"image":"https://media.rawg.io/media/screenshots/2d5/2d58ac7561c4168ea3ed7b0fb4fe7bc8.jpg"}]},{"id":22513,"slug":"uncharted-2-among-thieves","name":"Uncharted 2: Among Thieves","released":"2009-10-13","tba":false,"background_image":"https://media.rawg.io/media/games/74b/74b239f6ef0216a2f66e652d54abb2e6.jpg","rating":4.39,"rating_top":5,"ratings":[{"id":5,"title":"exceptional","count":964,"percent":56.37},{"id":4,"title":"recommended","count":577,"percent":33.74},{"id":3,"title":"meh","count":105,"percent":6.14},{"id":1,"title":"skip","count":64,"percent":3.74}],"ratings_count":1693,"reviews_text_count":11,"added":3835,"added_by_status":{"yet":127,"owned":1396,"beaten":2042,"toplay":163,"dropped":70,"playing":37},"metacritic":96,"playtime":13,"suggestions_count":647,"updated":"2024-01-21T19:14:18","user_game":null,"reviews_count":1710,"saturated_color":"0f0f0f","dominant_color":"0f0f0f","platforms":[{"platform":{"id":18,"name":"PlayStation 4","slug":"playstation4","image":null,"year_end":null,"year_start":null,"games_count":6744,"image_background":"https://media.rawg.io/media/games/4be/4be6a6ad0364751a96229c56bf69be59.jpg"},"released_at":"2009-10-13","requirements_en":null,"requirements_ru":null},{"platform":{"id":16,"name":"PlayStation 3","slug":"playstation3","image":null,"year_end":null,"year_start":null,"games_count":3161,"image_background":"https://media.rawg.io/media/games/d69/d69810315bd7e226ea2d21f9156af629.jpg"},"released_at":"2009-10-13","requirements_en":null,"requirements_ru":null}],"parent_platforms":[{"platform":{"id":2,"name":"PlayStation","slug":"playstation"}}],"genres":[{"id":4,"name":"Action","slug":"action","games_count":177743,"image_background":"https://media.rawg.io/media/games/49c/49c3dfa4ce2f6f140cc4825868e858cb.jpg"},{"id":2,"name":"Shooter","slug":"shooter","games_count":59432,"image_background":"https://media.rawg.io/media/games/34b/34b1f1850a1c06fd971bc6ab3ac0ce0e.jpg"},{"id":3,"name":"Adventure","slug":"adventure","games_count":137364,"image_background":"https://media.rawg.io/media/games/562/562553814dd54e001a541e4ee83a591c.jpg"}],"stores":[{"id":967773,"store":{"id":3,"name":"PlayStation Store","slug":"playstation-store","domain":"store.playstation.com","games_count":7878,"image_background":"https://media.rawg.io/media/games/157/15742f2f67eacff546738e1ab5c19d20.jpg"}}],"clip":null,"tags":[{"id":406,"name":"Story","slug":"story","language":"eng","games_count":11321,"image_background":"https://media.rawg.io/media/games/74b/74b239f6ef0216a2f66e652d54abb2e6.jpg"}],"esrb_rating":{"id":3,"name":"Teen","slug":"teen"},"short_screenshots":[{"id":-1,"image":"https://media.rawg.io/media/games/74b/74b239f6ef0216a2f66e652d54abb2e6.jpg"},{"id":510193,"image":"https://media.rawg.io/media/screenshots/c2a/c2a483758a22707799fec207a78d552f.jpg"},{"id":510194,"image":"https://media.rawg.io/media/screenshots/a93/a93fcf9216cd814573dc4aa5ea3a80c8.jpg"},{"id":510195,"image":"https://media.rawg.io/media/screenshots/51d/51d4bb10e5a9ff7111e6e40a9687aee5.jpg"},{"id":510196,"image":"https://media.rawg.io/media/screenshots/503/5030d91eac59ab5b28eb6bdb7e41313c.jpg"},{"id":510197,"image":"https://media.rawg.io/media/screenshots/442/4429d068cd37c213e40bb83fe9b7c65c.jpg"},{"id":510198,"image":"https://media.rawg.io/media/screenshots/366/366cb6c21d945376b185d4b2d94a59c2.jpg"}]},{"id":18080,"slug":"half-life","name":"Half-Life","released":"1998-11-08","tba":false,"background_image":"https://media.rawg.io/media/games/6c5/6c55e22185876626881b76c11922b073.jpg","rating":4.38,"rating_top":5,"ratings":[{"id":5,"title":"exceptional","count":1261,"percent":55.65},{"id":4,"title":"recommended","count":764,"percent":33.72},{"id":3,"title":"meh","count":162,"percent":7.15},{"id":1,"title":"skip","count":79,"percent":3.49}],"ratings_count":2247,"reviews_text_count":13,"added":10007,"added_by_status":{"yet":386,"owned":6491,"beaten":2362,"toplay":171,"dropped":537,"playing":60},"metacritic":96,"playtime":3,"suggestions_count":468,"updated":"2024-01-23T01:29:54","user_game":null,"reviews_count":2266,"saturated_color":"0f0f0f","dominant_color":"0f0f0f","platforms":[{"platform":{"id":106,"name":"Dreamcast","slug":"dreamcast","image":null,"year_end":null,"year_start":null,"games_count":360,"image_background":"https://media.rawg.io/media/games/4cb/4cb463b5588adc672124fb041f09e91c.jpg"},"released_at":"1998-11-08","requirements_en":null,"requirements_ru":null},{"platform":{"id":6,"name":"Linux","slug":"linux","image":null,"year_end":null,"year_start":null,"games_count":76309,"image_background":"https://media.rawg.io/media/games/b8c/b8c243eaa0fbac8115e0cdccac3f91dc.jpg"},"released_at":"1998-11-08","requirements_en":{"minimum":"Minimum: Linux Ubuntu 12.04, Dual-core from Intel or AMD at 2.8 GHz, 1GB Memory, nVidia GeForce 8600/9600GT, ATI/AMD Radeaon HD2600/3600 (Graphic Drivers: nVidia 310, AMD 12.11), OpenGL 2.1, 4GB Hard Drive Space, OpenAL Compatible Sound Card"},"requirements_ru":null},{"platform":{"id":5,"name":"macOS","slug":"macos","image":null,"year_end":null,"year_start":null,"games_count":103224,"image_background":"https://media.rawg.io/media/games/2ba/2bac0e87cf45e5b508f227d281c9252a.jpg"},"released_at":"1998-11-08","requirements_en":{"minimum":"Minimum: OS X  Snow Leopard 10.6.3, 1GB RAM, 4GB Hard Drive Space,NVIDIA GeForce 8 or higher, ATI X1600 or higher, or Intel HD 3000 or higher Mouse, Keyboard, Internet Connection"},"requirements_ru":null},{"platform":{"id":4,"name":"PC","slug":"pc","image":null,"year_end":null,"year_start":null,"games_count":524417,"image_background":"https://media.rawg.io/media/games/587/587588c64afbff80e6f444eb2e46f9da.jpg"},"released_at":"1998-11-08","requirements_en":{"minimum":"<p><strong>Minimum:</strong> 500 mhz processor, 96mb ram, 16mb video card, Windows XP, Mouse, Keyboard, Internet Connection<br /></p>\r\n\t\t\t<p><strong>Recommended:</strong> 800 mhz processor, 128mb ram, 32mb+ video card, Windows XP, Mouse, Keyboard, Internet Connection<br /></p>"},"requirements_ru":{"minimum":"Pentium 133, 32  ","recommended":"Pentium II 333 , 64  , 3D-"}},{"platform":{"id":15,"name":"PlayStation 2","slug":"playstation2","image":null,"year_end":null,"year_start":null,"games_count":2020,"image_background":"https://media.rawg.io/media/games/2ee/2eef5ed5e82c28d1299ecc2a0e60f2cb.jpg"},"released_at":"1998-11-08","requirements_en":null,"requirements_ru":null}],"parent_platforms":[{"platform":{"id":1,"name":"PC","slug":"pc"}},{"platform":{"id":2,"name":"PlayStation","slug":"playstation"}},{"platform":{"id":5,"name":"Apple Macintosh","slug":"mac"}},{"platform":{"id":6,"name":"Linux","slug":"linux"}},{"platform":{"id":11,"name":"SEGA","slug":"sega"}}],"genres":[{"id":4,"name":"Action","slug":"action","games_count":177743,"image_background":"https://media.rawg.io/media/games/49c/49c3dfa4ce2f6f140cc4825868e858cb.jpg"},{"id":2,"name":"Shooter","slug":"shooter","games_count":59432,"image_background":"https://media.rawg.io/media/games/34b/34b1f1850a1c06fd971bc6ab3ac0ce0e.jpg"}],"stores":[{"id":20250,"store":{"id":1,"name":"Steam","slug":"steam","domain":"store.steampowered.com","games_count":87632,"image_background":"https://media.rawg.io/media/games/490/49016e06ae2103881ff6373248843069.jpg"}}],"clip":null,"tags":[{"id":31,"name":"Singleplayer","slug":"singleplayer","language":"eng","games_count":216849,"image_background":"https://media.rawg.io/media/games/4a0/4a0a1316102366260e6f38fd2a9cfdce.jpg"},{"id":7,"name":"Multiplayer","slug":"multiplayer","language":"eng","games_count":36937,"image_background":"https://media.rawg.io/media/games/587/587588c64afbff80e6f444eb2e46f9da.jpg"},{"id":13,"name":"Atmospheric","slug":"atmospheric","language":"eng","games_count":31740,"image_background":"https://media.rawg.io/media/games/490/49016e06ae2103881ff6373248843069.jpg"},{"id":42,"name":"Great Soundtrack","slug":"great-soundtrack","language":"eng","games_count":3381,"image_background":"https://media.rawg.io/media/games/511/5118aff5091cb3efec399c808f8c598f.jpg"},{"id":118,"name":"Story Rich","slug":"story-rich","language":"eng","games_count":20253,"image_background":"https://media.rawg.io/media/games/198/1988a337305e008b41d7f536ce9b73f6.jpg"},{"id":8,"name":"First-Person","slug":"first-person","language":"eng","games_count":30386,"image_background":"https://media.rawg.io/media/games/fc1/fc1307a2774506b5bd65d7e8424664a7.jpg"},{"id":32,"name":"Sci-fi","slug":"sci-fi","language":"eng","games_count":18374,"image_background":"https://media.rawg.io/media/games/9dd/9ddabb34840ea9227556670606cf8ea3.jpg"},{"id":30,"name":"FPS","slug":"fps","language":"eng","games_count":12796,"image_background":"https://media.rawg.io/media/games/d58/d588947d4286e7b5e0e12e1bea7d9844.jpg"},{"id":4,"name":"Funny","slug":"funny","language":"eng","games_count":23984,"image_background":"https://media.rawg.io/media/games/25c/25c4776ab5723d5d735d8bf617ca12d9.jpg"},{"id":49,"name":"Difficult","slug":"difficult","language":"eng","games_count":13012,"image_background":"https://media.rawg.io/media/games/daa/daaee07fcb40744d90cf8142f94a241f.jpg"},{"id":193,"name":"Classic","slug":"classic","language":"eng","games_count":1781,"image_background":"https://media.rawg.io/media/games/4a0/4a0a1316102366260e6f38fd2a9cfdce.jpg"},{"id":74,"name":"Retro","slug":"retro","language":"eng","games_count":40880,"image_background":"https://media.rawg.io/media/games/501/501e7019925a3c692bf1c8062f07abe6.jpg"},{"id":62,"name":"Moddable","slug":"moddable","language":"eng","games_count":866,"image_background":"https://media.rawg.io/media/games/7a2/7a2500ee8b2c0e1ff268bb4479463dea.jpg"},{"id":172,"name":"Aliens","slug":"aliens","language":"eng","games_count":6563,"image_background":"https://media.rawg.io/media/games/b7b/b7b8381707152afc7d91f5d95de70e39.jpg"},{"id":40856,"name":"Valve Anti-Cheat enabled","slug":"valve-anti-cheat-enabled","language":"eng","games_count":105,"image_background":"https://media.rawg.io/media/games/78d/78dfae12fb8c5b16cd78648553071e0a.jpg"},{"id":243,"name":"1990's","slug":"1990s","language":"eng","games_count":2238,"image_background":"https://media.rawg.io/media/games/38a/38af969459ad6e5de116ec8a4a84218c.jpg"},{"id":305,"name":"Linear","slug":"linear","language":"eng","games_count":5251,"image_background":"https://media.rawg.io/media/games/a14/a14acef284eaa4854f83c99e80fc15d8.jpg"},{"id":319,"name":"Silent Protagonist","slug":"silent-protagonist","language":"eng","games_count":91,"image_background":"https://media.rawg.io/media/games/198/1988a337305e008b41d7f536ce9b73f6.jpg"},{"id":62349,"name":"vr mod","slug":"vr-mod","language":"eng","games_count":17,"image_background":"https://media.rawg.io/media/screenshots/1bb/1bb3f78f0fe43b5d5ca2f3da5b638840.jpg"}],"esrb_rating":{"id":4,"name":"Mature","slug":"mature"},"short_screenshots":[{"id":-1,"image":"https://media.rawg.io/media/games/6c5/6c55e22185876626881b76c11922b073.jpg"},{"id":167835,"image":"https://media.rawg.io/media/screenshots/345/3458269ae8ea44a6b8c8268d39fe36a1.jpg"},{"id":167836,"image":"https://media.rawg.io/media/screenshots/3c5/3c55c835054009de798c0a9fa886ef8b.jpg"},{"id":167837,"image":"https://media.rawg.io/media/screenshots/700/70005f6c84708d988a287d406cbb038c.jpg"},{"id":167838,"image":"https://media.rawg.io/media/screenshots/755/755a2b42257cf09c7f37e902dfa08400.jpg"},{"id":167839,"image":"https://media.rawg.io/media/screenshots/921/9213ce16eba80f51b3562a3e5d322e02.jpg"},{"id":167840,"image":"https://media.rawg.io/media/screenshots/948/948de39d02c1f08c8c98fa10e69e87af.jpg"}]},{"id":13537,"slug":"half-life-2","name":"Half-Life 2","released":"2004-11-16","tba":false,"background_image":"https://media.rawg.io/media/games/b8c/b8c243eaa0fbac8115e0cdccac3f91dc.jpg","rating":4.49,"rating_top":5,"ratings":[{"id":5,"title":"exceptional","count":2434,"percent":63.7},{"id":4,"title":"recommended","count":1048,"percent":27.43},{"id":3,"title":"meh","count":219,"percent":5.73},{"id":1,"title":"skip","count":120,"percent":3.14}],"ratings_count":3797,"reviews_text_count":17,"added":14152,"added_by_status":{"yet":647,"owned":8902,"beaten":3662,"toplay":306,"dropped":545,"playing":90},"metacritic":96,"playtime":7,"suggestions_count":553,"updated":"2024-01-23T12:13:45","user_game":null,"reviews_count":3821,"saturated_color":"0f0f0f","dominant_color":"0f0f0f","platforms":[{"platform":{"id":4,"name":"PC","slug":"pc","image":null,"year_end":null,"year_start":null,"games_count":524417,"image_background":"https://media.rawg.io/media/games/587/587588c64afbff80e6f444eb2e46f9da.jpg"},"released_at":"2004-11-16","requirements_en":{"minimum":"Minimum:\r\n\r\nOS: Windows 7, Vista, XP\r\n\r\nProcessor: 1.7 Ghz\r\n\r\nMemory: 512 MB RAM\r\n\r\nGraphics: DirectX 8.1 level Graphics Card (requires support for SSE)\r\n\r\nStorage: 6500 MB available space"},"requirements_ru":{"minimum":"Pentium III/Athlon 1.2 ,256  ,3D-  64  ,5   ,  ","recommended":"Pentium 4/Athlon XP 2.5 ,512  ,3D-  128  ,5   ,  "}},{"platform":{"id":5,"name":"macOS","slug":"macos","image":null,"year_end":null,"year_start":null,"games_count":103224,"image_background":"https://media.rawg.io/media/games/2ba/2bac0e87cf45e5b508f227d281c9252a.jpg"},"released_at":"2004-11-16","requirements_en":{"minimum":"Minimum:\r\n\r\nOS: Leopard 10.5.8, Snow Leopard 10.6.3, or higher\r\n\r\nMemory: 1 GB RAM\r\n\r\nGraphics: Nvidia GeForce8 or higher, ATI X1600 or higher, Intel HD 3000 or higher"},"requirements_ru":null},{"platform":{"id":14,"name":"Xbox 360","slug":"xbox360","image":null,"year_end":null,"year_start":null,"games_count":2787,"image_background":"https://media.rawg.io/media/games/15c/15c95a4915f88a3e89c821526afe05fc.jpg"},"released_at":"2004-11-16","requirements_en":null,"requirements_ru":null},{"platform":{"id":6,"name":"Linux","slug":"linux","image":null,"year_end":null,"year_start":null,"games_count":76309,"image_background":"https://media.rawg.io/media/games/b8c/b8c243eaa0fbac8115e0cdccac3f91dc.jpg"},"released_at":"2004-11-16","requirements_en":null,"requirements_ru":null},{"platform":{"id":80,"name":"Xbox","slug":"xbox-old","image":null,"year_end":null,"year_start":null,"games_count":735,"image_background":"https://media.rawg.io/media/games/99b/99b39612e864d6ddfdb2c407fd9010a1.jpg"},"released_at":"2004-11-16","requirements_en":null,"requirements_ru":null},{"platform":{"id":21,"name":"Android","slug":"android","image":null,"year_end":null,"year_start":null,"games_count":52312,"image_background":"https://media.rawg.io/media/games/be0/be084b850302abe81675bc4ffc08a0d0.jpg"},"released_at":"2004-11-16","requirements_en":{"minimum":"4.4 and up"},"requirements_ru":null}],"parent_platforms":[{"platform":{"id":1,"name":"PC","slug":"pc"}},{"platform":{"id":3,"name":"Xbox","slug":"xbox"}},{"platform":{"id":8,"name":"Android","slug":"android"}},{"platform":{"id":5,"name":"Apple Macintosh","slug":"mac"}},{"platform":{"id":6,"name":"Linux","slug":"linux"}}],"genres":[{"id":4,"name":"Action","slug":"action","games_count":177743,"image_background":"https://media.rawg.io/media/games/49c/49c3dfa4ce2f6f140cc4825868e858cb.jpg"},{"id":2,"name":"Shooter","slug":"shooter","games_count":59432,"image_background":"https://media.rawg.io/media/games/34b/34b1f1850a1c06fd971bc6ab3ac0ce0e.jpg"}],"stores":[{"id":14891,"store":{"id":1,"name":"Steam","slug":"steam","domain":"store.steampowered.com","games_count":87632,"image_background":"https://media.rawg.io/media/games/490/49016e06ae2103881ff6373248843069.jpg"}},{"id":41441,"store":{"id":8,"name":"Google Play","slug":"google-play","domain":"play.google.com","games_count":17073,"image_background":"https://media.rawg.io/media/games/35b/35b47c4d85cd6e08f3e2ca43ea5ce7bb.jpg"}}],"clip":null,"tags":[{"id":31,"name":"Singleplayer","slug":"singleplayer","language":"eng","games_count":216849,"image_background":"https://media.rawg.io/media/games/4a0/4a0a1316102366260e6f38fd2a9cfdce.jpg"},{"id":40847,"name":"Steam Achievements","slug":"steam-achievements","language":"eng","games_count":35163,"image_background":"https://media.rawg.io/media/games/310/3106b0e012271c5ffb16497b070be739.jpg"},{"id":7,"name":"Multiplayer","slug":"multiplayer","language":"eng","games_count":36937,"image_background":"https://media.rawg.io/media/games/587/587588c64afbff80e6f444eb2e46f9da.jpg"},{"id":40849,"name":"Steam Cloud","slug":"steam-cloud","language":"eng","games_count":16509,"image_background":"https://media.rawg.io/media/games/490/49016e06ae2103881ff6373248843069.jpg"},{"id":13,"name":"Atmospheric","slug":"atmospheric","language":"eng","games_count":31740,"image_background":"https://media.rawg.io/media/games/490/49016e06ae2103881ff6373248843069.jpg"},{"id":7808,"name":"steam-trading-cards","slug":"steam-trading-cards","language":"eng","games_count":7569,"image_background":"https://media.rawg.io/media/games/73e/73eecb8909e0c39fb246f457b5d6cbbe.jpg"},{"id":42,"name":"Great Soundtrack","slug":"great-soundtrack","language":"eng","games_count":3381,"image_background":"https://media.rawg.io/media/games/511/5118aff5091cb3efec399c808f8c598f.jpg"},{"id":118,"name":"Story Rich","slug":"story-rich","language":"eng","games_count":20253,"image_background":"https://media.rawg.io/media/games/198/1988a337305e008b41d7f536ce9b73f6.jpg"},{"id":8,"name":"First-Person","slug":"first-person","language":"eng","games_count":30386,"image_background":"https://media.rawg.io/media/games/fc1/fc1307a2774506b5bd65d7e8424664a7.jpg"},{"id":32,"name":"Sci-fi","slug":"sci-fi","language":"eng","games_count":18374,"image_background":"https://media.rawg.io/media/games/9dd/9ddabb34840ea9227556670606cf8ea3.jpg"},{"id":40845,"name":"Partial Controller Support","slug":"partial-controller-support","language":"eng","games_count":11086,"image_background":"https://media.rawg.io/media/games/f87/f87457e8347484033cb34cde6101d08d.jpg"},{"id":16,"name":"Horror","slug":"horror","language":"eng","games_count":43337,"image_background":"https://media.rawg.io/media/games/dd5/dd50d4266915d56dd5b63ae1bf72606a.jpg"},{"id":30,"name":"FPS","slug":"fps","language":"eng","games_count":12796,"image_background":"https://media.rawg.io/media/games/d58/d588947d4286e7b5e0e12e1bea7d9844.jpg"},{"id":193,"name":"Classic","slug":"classic","language":"eng","games_count":1781,"image_background":"https://media.rawg.io/media/games/4a0/4a0a1316102366260e6f38fd2a9cfdce.jpg"},{"id":63,"name":"Zombies","slug":"zombies","language":"eng","games_count":10065,"image_background":"https://media.rawg.io/media/games/cee/cee577e2097a59b77193fe2bce94667d.jpg"},{"id":62,"name":"Moddable","slug":"moddable","language":"eng","games_count":866,"image_background":"https://media.rawg.io/media/games/7a2/7a2500ee8b2c0e1ff268bb4479463dea.jpg"},{"id":40833,"name":"Captions available","slug":"captions-available","language":"eng","games_count":1302,"image_background":"https://media.rawg.io/media/games/490/49016e06ae2103881ff6373248843069.jpg"},{"id":114,"name":"Physics","slug":"physics","language":"eng","games_count":18685,"image_background":"https://media.rawg.io/media/games/a3c/a3c529a12c896c0ef02db5b4741de2ba.jpg"},{"id":172,"name":"Aliens","slug":"aliens","language":"eng","games_count":6563,"image_background":"https://media.rawg.io/media/games/b7b/b7b8381707152afc7d91f5d95de70e39.jpg"},{"id":119,"name":"Dystopian","slug":"dystopian","language":"eng","games_count":1971,"image_background":"https://media.rawg.io/media/games/7c4/7c448374df84b607f67ce9182a3a3ca7.jpg"},{"id":40839,"name":"Includes Source SDK","slug":"includes-source-sdk","language":"eng","games_count":62,"image_background":"https://media.rawg.io/media/screenshots/ae8/ae873e0da5973a9896bdf5ebce1e9bf4.jpg"},{"id":319,"name":"Silent Protagonist","slug":"silent-protagonist","language":"eng","games_count":91,"image_background":"https://media.rawg.io/media/games/198/1988a337305e008b41d7f536ce9b73f6.jpg"},{"id":62349,"name":"vr mod","slug":"vr-mod","language":"eng","games_count":17,"image_background":"https://media.rawg.io/media/screenshots/1bb/1bb3f78f0fe43b5d5ca2f3da5b638840.jpg"}],"esrb_rating":{"id":4,"name":"Mature","slug":"mature"},"short_screenshots":[{"id":-1,"image":"https://media.rawg.io/media/games/b8c/b8c243eaa0fbac8115e0cdccac3f91dc.jpg"},{"id":115804,"image":"https://media.rawg.io/media/screenshots/8af/8af6188357426890cbc8c8a34d9e7b75.jpg"},{"id":115805,"image":"https://media.rawg.io/media/screenshots/3b5/3b542c954ba5bd2f32da067c8122cd80.jpg"},{"id":115806,"image":"https://media.rawg.io/media/screenshots/3d6/3d6066e45d259d2e83bf6767e6113d94.jpg"},{"id":115807,"image":"https://media.rawg.io/media/screenshots/e49/e49327df2404df6c5dafa8eac7990852.jpg"},{"id":115808,"image":"https://media.rawg.io/media/screenshots/5dd/5dd3e53131bbfe6278bd15b9abe261a0.jpg"},{"id":115809,"image":"https://media.rawg.io/media/screenshots/e99/e995e154d4f9e2df0367adea528a72c5.jpg"}]},{"id":4286,"slug":"bioshock","name":"BioShock","released":"2007-08-21","tba":false,"background_image":"https://media.rawg.io/media/games/bc0/bc06a29ceac58652b684deefe7d56099.jpg","rating":4.36,"rating_top":5,"ratings":[{"id":5,"title":"exceptional","count":1715,"percent":52.83},{"id":4,"title":"recommended","count":1186,"percent":36.54},{"id":3,"title":"meh","count":241,"percent":7.42},{"id":1,"title":"skip","count":104,"percent":3.2}],"ratings_count":3205,"reviews_text_count":25,"added":13508,"added_by_status":{"yet":613,"owned":8629,"beaten":3119,"toplay":325,"dropped":712,"playing":110},"metacritic":96,"playtime":3,"suggestions_count":645,"updated":"2024-01-23T01:46:05","user_game":null,"reviews_count":3246,"saturated_color":"0f0f0f","dominant_color":"0f0f0f","platforms":[{"platform":{"id":16,"name":"PlayStation 3","slug":"playstation3","image":null,"year_end":null,"year_start":null,"games_count":3161,"image_background":"https://media.rawg.io/media/games/d69/d69810315bd7e226ea2d21f9156af629.jpg"},"released_at":"2007-08-21","requirements_en":null,"requirements_ru":null},{"platform":{"id":5,"name":"macOS","slug":"macos","image":null,"year_end":null,"year_start":null,"games_count":103224,"image_background":"https://media.rawg.io/media/games/2ba/2bac0e87cf45e5b508f227d281c9252a.jpg"},"released_at":"2007-08-21","requirements_en":null,"requirements_ru":null},{"platform":{"id":4,"name":"PC","slug":"pc","image":null,"year_end":null,"year_start":null,"games_count":524417,"image_background":"https://media.rawg.io/media/games/587/587588c64afbff80e6f444eb2e46f9da.jpg"},"released_at":"2007-08-21","requirements_en":{"minimum":"<h2 class=\"bb_tag\"><strong>Minimum: </strong></h2><ul class=\"bb_ul\"><li><strong>Operating System</strong>: Windows XP (with Service Pack 2) or Windows Vista<br></li><li><strong>CPU</strong>: Intel single-core Pentium 4 processor at 2.4GHz<br></li><li><strong>RAM</strong>: 1 GB<br></li><li><strong>Video Card</strong>: Direct X 9.0c compliant video card with 128MB RAM and Pixel Shader 3.0 (NVIDIA 6600 or better/ATI X1300 or better, excluding ATI X1550)<br></li><li><strong>Sound Card</strong>: 100% direct X 9.0c compatible sound card<br></li><li><strong>Hard Drive Space</strong>: 8GB<br></li><li>Game requires Internet connection for activation</li></ul>","recommended":"<h2 class=\"bb_tag\"><strong>Recommended: </strong></h2><ul class=\"bb_ul\"><li><strong>CPU</strong>: Intel Core 2 Duo processor<br></li><li><strong>RAM</strong>: 2GB<br></li><li><strong>Video Card</strong>: DX 9 - Direct X 9.0c compliant video card with 512 MB RAM and Pixel Shader 3.0 (NVIDIA GeForce 7900 GT or better), DX 10 - NVIDIA GeForce 8600 or better<br></li><li><strong>Sound Card</strong>: SoundBlaster(r) X-Fi(tm) series (optimized foruse with Creative Labs EAX ADVANCED HD 4.0 or EAX ADVANCED HD 5.0 compatible sound cards)</li></ul>"},"requirements_ru":{"minimum":"Pentium 4/Athlon 64 2.5 ,1  ,3D-  128    SM 3.0, 7.5   , Windows XP SP2  Vista,-","recommended":"Core 2 Duo/Athlon 64 X2 3 ,2  ,3D-  512    SM 3.0, 7.5   , Windows Vista,-"}},{"platform":{"id":14,"name":"Xbox 360","slug":"xbox360","image":null,"year_end":null,"year_start":null,"games_count":2787,"image_background":"https://media.rawg.io/media/games/15c/15c95a4915f88a3e89c821526afe05fc.jpg"},"released_at":"2007-08-21","requirements_en":null,"requirements_ru":null}],"parent_platforms":[{"platform":{"id":1,"name":"PC","slug":"pc"}},{"platform":{"id":2,"name":"PlayStation","slug":"playstation"}},{"platform":{"id":3,"name":"Xbox","slug":"xbox"}},{"platform":{"id":5,"name":"Apple Macintosh","slug":"mac"}}],"genres":[{"id":4,"name":"Action","slug":"action","games_count":177743,"image_background":"https://media.rawg.io/media/games/49c/49c3dfa4ce2f6f140cc4825868e858cb.jpg"},{"id":2,"name":"Shooter","slug":"shooter","games_count":59432,"image_background":"https://media.rawg.io/media/games/34b/34b1f1850a1c06fd971bc6ab3ac0ce0e.jpg"}],"stores":[{"id":4614,"store":{"id":3,"name":"PlayStation Store","slug":"playstation-store","domain":"store.playstation.com","games_count":7878,"image_background":"https://media.rawg.io/media/games/157/15742f2f67eacff546738e1ab5c19d20.jpg"}},{"id":79531,"store":{"id":4,"name":"App Store","slug":"apple-appstore","domain":"apps.apple.com","games_count":75399,"image_background":"https://media.rawg.io/media/games/bc0/bc06a29ceac58652b684deefe7d56099.jpg"}},{"id":440407,"store":{"id":2,"name":"Xbox Store","slug":"xbox-store","domain":"microsoft.com","games_count":4790,"image_background":"https://media.rawg.io/media/games/8d6/8d69eb6c32ed6acfd75f82d532144993.jpg"}},{"id":20580,"store":{"id":1,"name":"Steam","slug":"steam","domain":"store.steampowered.com","games_count":87632,"image_background":"https://media.rawg.io/media/games/490/49016e06ae2103881ff6373248843069.jpg"}},{"id":33844,"store":{"id":7,"name":"Xbox 360 Store","slug":"xbox360","domain":"marketplace.xbox.com","games_count":1912,"image_background":"https://media.rawg.io/media/games/960/960b601d9541cec776c5fa42a00bf6c4.jpg"}}],"clip":null,"tags":[{"id":31,"name":"Singleplayer","slug":"singleplayer","language":"eng","games_count":216849,"image_background":"https://media.rawg.io/media/games/4a0/4a0a1316102366260e6f38fd2a9cfdce.jpg"},{"id":13,"name":"Atmospheric","slug":"atmospheric","language":"eng","games_count":31740,"image_background":"https://media.rawg.io/media/games/490/49016e06ae2103881ff6373248843069.jpg"},{"id":42,"name":"Great Soundtrack","slug":"great-soundtrack","language":"eng","games_count":3381,"image_background":"https://media.rawg.io/media/games/511/5118aff5091cb3efec399c808f8c598f.jpg"},{"id":24,"name":"RPG","slug":"rpg","language":"eng","games_count":19541,"image_background":"https://media.rawg.io/media/games/b45/b45575f34285f2c4479c9a5f719d972e.jpg"},{"id":118,"name":"Story Rich","slug":"story-rich","language":"eng","games_count":20253,"image_background":"https://media.rawg.io/media/games/198/1988a337305e008b41d7f536ce9b73f6.jpg"},{"id":8,"name":"First-Person","slug":"first-person","language":"eng","games_count":30386,"image_background":"https://media.rawg.io/media/games/fc1/fc1307a2774506b5bd65d7e8424664a7.jpg"},{"id":32,"name":"Sci-fi","slug":"sci-fi","language":"eng","games_count":18374,"image_background":"https://media.rawg.io/media/games/9dd/9ddabb34840ea9227556670606cf8ea3.jpg"},{"id":40845,"name":"Partial Controller Support","slug":"partial-controller-support","language":"eng","games_count":11086,"image_background":"https://media.rawg.io/media/games/f87/f87457e8347484033cb34cde6101d08d.jpg"},{"id":16,"name":"Horror","slug":"horror","language":"eng","games_count":43337,"image_background":"https://media.rawg.io/media/games/dd5/dd50d4266915d56dd5b63ae1bf72606a.jpg"},{"id":30,"name":"FPS","slug":"fps","language":"eng","games_count":12796,"image_background":"https://media.rawg.io/media/games/d58/d588947d4286e7b5e0e12e1bea7d9844.jpg"},{"id":193,"name":"Classic","slug":"classic","language":"eng","games_count":1781,"image_background":"https://media.rawg.io/media/games/4a0/4a0a1316102366260e6f38fd2a9cfdce.jpg"},{"id":97,"name":"Action RPG","slug":"action-rpg","language":"eng","games_count":6400,"image_background":"https://media.rawg.io/media/games/d0f/d0f91fe1d92332147e5db74e207cfc7a.jpg"},{"id":41,"name":"Dark","slug":"dark","language":"eng","games_count":15072,"image_background":"https://media.rawg.io/media/games/744/744adc36e6573dd67a0cb0e373738d19.jpg"},{"id":119,"name":"Dystopian","slug":"dystopian","language":"eng","games_count":1971,"image_background":"https://media.rawg.io/media/games/7c4/7c448374df84b607f67ce9182a3a3ca7.jpg"},{"id":154,"name":"Steampunk","slug":"steampunk","language":"eng","games_count":1167,"image_background":"https://media.rawg.io/media/games/95a/95adc7a2135783dfd2204f694200c836.jpg"},{"id":208,"name":"Alternate History","slug":"alternate-history","language":"eng","games_count":1650,"image_background":"https://media.rawg.io/media/games/bc0/bc06a29ceac58652b684deefe7d56099.jpg"},{"id":287,"name":"Political","slug":"political","language":"eng","games_count":572,"image_background":"https://media.rawg.io/media/games/6d3/6d33014a4ed48a19c30a77ead5a0f62e.jpg"},{"id":250,"name":"Underwater","slug":"underwater","language":"eng","games_count":2039,"image_background":"https://media.rawg.io/media/games/bc0/bc06a29ceac58652b684deefe7d56099.jpg"}],"esrb_rating":{"id":4,"name":"Mature","slug":"mature"},"short_screenshots":[{"id":-1,"image":"https://media.rawg.io/media/games/bc0/bc06a29ceac58652b684deefe7d56099.jpg"},{"id":170993,"image":"https://media.rawg.io/media/screenshots/01f/01f62d7064838a5c3202acfc61503487.jpg"},{"id":170994,"image":"https://media.rawg.io/media/screenshots/7f5/7f517e07e36e4af5a7c0b86a7d42853f.jpg"},{"id":170995,"image":"https://media.rawg.io/media/screenshots/aca/aca089b963a42ec4cbf56b5e5334af8e.jpg"},{"id":170996,"image":"https://media.rawg.io/media/screenshots/3aa/3aa6f71eba1d64e671bd45826ca96560.jpg"},{"id":170997,"image":"https://media.rawg.io/media/screenshots/d8e/d8ed29c7c0b41e4013588847944ed446.jpg"},{"id":170998,"image":"https://media.rawg.io/media/screenshots/146/146e418797aca19296f90d259207414c.jpg"}]}],"seo_title":"All Games","seo_description":"","seo_keywords":"","seo_h1":"All Games","noindex":false,"nofollow":false,"description":"","filters":{"years":[{"from":2020,"to":2024,"filter":"2020-01-01,2024-12-31","decade":2020,"years":[{"year":2024,"count":757,"nofollow":false},{"year":2023,"count":61848,"nofollow":false},{"year":2022,"count":168117,"nofollow":false},{"year":2021,"count":158673,"nofollow":false},{"year":2020,"count":121344,"nofollow":false}],"nofollow":true,"count":510739},{"from":2010,"to":2019,"filter":"2010-01-01,2019-12-31","decade":2010,"years":[{"year":2019,"count":73680,"nofollow":false},{"year":2018,"count":67932,"nofollow":false},{"year":2017,"count":54585,"nofollow":true},{"year":2016,"count":40243,"nofollow":true},{"year":2015,"count":25893,"nofollow":true},{"year":2014,"count":15357,"nofollow":true},{"year":2013,"count":6336,"nofollow":true},{"year":2012,"count":5390,"nofollow":true},{"year":2011,"count":4314,"nofollow":true},{"year":2010,"count":3895,"nofollow":true}],"nofollow":true,"count":297625},{"from":2000,"to":2009,"filter":"2000-01-01,2009-12-31","decade":2000,"years":[{"year":2009,"count":3113,"nofollow":true},{"year":2008,"count":2044,"nofollow":true},{"year":2007,"count":1585,"nofollow":true},{"year":2006,"count":1302,"nofollow":true},{"year":2005,"count":1190,"nofollow":true},{"year":2004,"count":1187,"nofollow":true},{"year":2003,"count":1165,"nofollow":true},{"year":2002,"count":1017,"nofollow":true},{"year":2001,"count":1145,"nofollow":true},{"year":2000,"count":1039,"nofollow":true}],"nofollow":true,"count":14787},{"from":1990,"to":1999,"filter":"1990-01-01,1999-12-31","decade":1990,"years":[{"year":1999,"count":808,"nofollow":true},{"year":1998,"count":750,"nofollow":true},{"year":1997,"count":877,"nofollow":true},{"year":1996,"count":784,"nofollow":true},{"year":1995,"count":875,"nofollow":true},{"year":1994,"count":830,"nofollow":true},{"year":1993,"count":754,"nofollow":true},{"year":1992,"count":664,"nofollow":true},{"year":1991,"count":586,"nofollow":true},{"year":1990,"count":543,"nofollow":true}],"nofollow":true,"count":7471},{"from":1980,"to":1989,"filter":"1980-01-01,1989-12-31","decade":1980,"years":[{"year":1989,"count":438,"nofollow":true},{"year":1988,"count":326,"nofollow":true},{"year":1987,"count":345,"nofollow":true},{"year":1986,"count":253,"nofollow":true},{"year":1985,"count":230,"nofollow":true},{"year":1984,"count":185,"nofollow":true},{"year":1983,"count":207,"nofollow":true},{"year":1982,"count":149,"nofollow":true},{"year":1981,"count":66,"nofollow":true},{"year":1980,"count":35,"nofollow":true}],"nofollow":true,"count":2234},{"from":1970,"to":1979,"filter":"1970-01-01,1979-12-31","decade":1970,"years":[{"year":1979,"count":15,"nofollow":true},{"year":1978,"count":17,"nofollow":true},{"year":1977,"count":13,"nofollow":true},{"year":1976,"count":7,"nofollow":true},{"year":1975,"count":3,"nofollow":true},{"year":1974,"count":2,"nofollow":true},{"year":1973,"count":1,"nofollow":true},{"year":1972,"count":2,"nofollow":true},{"year":1971,"count":6,"nofollow":true},{"year":1970,"count":1,"nofollow":true}],"nofollow":true,"count":67},{"from":1960,"to":1969,"filter":"1960-01-01,1969-12-31","decade":1960,"years":[{"year":1962,"count":1,"nofollow":true}],"nofollow":true,"count":1},{"from":1950,"to":1959,"filter":"1950-01-01,1959-12-31","decade":1950,"years":[{"year":1958,"count":1,"nofollow":true},{"year":1954,"count":1,"nofollow":true}],"nofollow":true,"count":2}]},"nofollow_collections":["stores"]}